{"title": "part0016_split_001", "index": 62, "content": [{"type": "text", "value": "§. 309.\n灵魂不仅仅自为地是非物质性的，而是自然的普遍的非物质性，以及自然单纯的观念性生命。作为在自己内存在的主体性和肉体性的直接同一性，灵魂是绝对的实体，而这样的同一性作为普遍的本质，依然是它的特殊化与个别化的绝对基础，但是在这种抽象规定内只是精神的睡眠状态。\n只有当一方面把物质想象为一种真理的东西，另一方面又把精神想象为一种事物，关于灵魂非物质性的问题才仍然能够具有一种意趣。但是，甚至物理学家们在近些时期也来谈论作为热、光等等一类的无重的原素了，其实他们似乎能够轻易地就把空间和时间也算进来。然而这些无重的东西另外也还有一种感性的定在，有一种己外存在。人们可以发现生命物质也被列入那个范围之中，但这种物质不只缺少重，而且也缺少其他每种定在，依这类定在它似乎还可以算入物质性东西。实际上，在生命的理念中自然的己外存在已经是自在地被扬弃了的，并且概念是生命的实体。但精神的实存并不是作为直接个别性的个别性，而是作为绝对否定性，是自由，在精神中，在概念中，那种己外存在已完全消失，化为概念的主观观念性，化为普遍性。与此有关的另一个问题是关于灵魂与肉体相通的问题。两者的相通过去已被认定为事实，因此问题仅仅在于，如何可以理解它？惯常的回答可以说是，它是一种不可理解的秘密。因为事实上如果两者被先假定为彼此绝对独立的东西，那么它们相互而言恰恰就是被认定为不可贯通的，正像每种物质与另一种物质对立起来被认定是不可贯通，并只是处于它们双方的非存在、处于它们的细孔之内的一样。但是，一切哲学家自这一关系成为问题以来所提供的回答，却不能看作是与上述回答同义的。笛卡尔、马勒伯朗士、斯宾诺莎、莱布尼茨曾无例外地把上帝陈述为这种关联，而且是在以下意义上的关联：有限的灵魂与物质不具有什么真理性，所以上帝并非单单是替换上述不可理解性的另一个语词，而毋宁说是灵魂与物质的真正的同一性。不过，这种同一性在这里还不能直接理解为上帝，因为它还不具有这一规定，而只方才具有自然精神的规定，或者说作为普遍灵魂的灵魂本身的规定。在这种灵魂中，物质作为一种单纯的思想或作为普遍的东西在自己的真理性内。然而，这种灵魂本身必不可丝毫再被作为世界灵魂给固定下来，因为它只是普遍性实体，这种实体只是作为个别性具有现实的真理性。\n§. 310.\n精神首先是这种直接向自然内沉入的存在，a）是在其自然规定性之内的灵魂；b）但灵魂却作为特殊的东西前来同它的这一无意识性发生对立；c）灵魂在作为它的肉体性的这种无意识性中是现实的。\na. 灵魂的自然规定性.\n§. 311.\n精神作为抽象的自然灵魂是单纯的恒星和地球的生命，是古人说的“奴斯”，即单纯的无意识的思想，而这种思想α）作为这种普遍性的本质是内在的理念，并且仿佛在处于它背后的自然的外在性那里具有它的现实性。但是，正如它作为灵魂是直接性的实体，它的定在乃是这一实体自然存在的特殊化，是一种直接性的自然规定性，这一规定性在个体性的地球上具有自己先已假定的现实性。\n§. 312.\n自然精神的普遍行星生命在自己那里具有地球这一区别而作为直接的差异，因此自然精神分解为种种特殊的自然精神，它们以整体表现地理上各大洲的自然，并构成种族差异。\n通过地球两极性的对立，陆地布局向北较为靠拢连属，并对海洋拥有优势，但朝向南半球却分离开来，彼此走成尖状，这种对立同时给各大洲的区别带来了已由特雷维拉奴斯从动物和植物方面所指出的一种变形（生物学，第Ⅱ部分）。\n§. 313.\n这一区别可出显成自然的偶然性，可出显成人们可称为地方精神的种种局部性状，并且在外在生活方式、生计、身体构造和素质方面这些性状会把自己显示出来，而尤为更多的是从内在倾向及理智与伦理性格的禀赋方面显示出来。\n§. 314.\n灵魂如同一般自在的概念那样，把自己个别化为个体性的主体。但这种主体性在这里只是作为自然规定性的个别化来加以考虑，它是作为不同气质、性格、面相的以及家族或单个个体其他素质的模式。\n§. 315.\nβ）直接的判断是个别灵魂的觉醒，这种觉醒是与首先作为自然规定性的、灵魂的无意识自然生活相对立而出现的，并作为一种状态与一种状态，即睡眠相对立而出现。个别性的这一转化与个体性的普遍身体，即地球相互联系着。\n§. 316.\n醒并不［单单］是对我们、或者是外在地同睡眠相区别，而应该说醒本身是个体灵魂的判断，因而是这种灵魂自身同自己未被区别的普遍性相互区别。一般地说，精神的一切自我意识的和理性的活动都属于觉醒存在。睡眠之是赋予这种活动以力量，并非是作为这种活动的静止（把有生命的活动看作力，宁可说它是沉睡在自己缺乏表现的状态），而是作为从种种规定性的世界、消遣娱乐和从囿于琐事，向主体性的普遍本质的回归，这种主体性是绝对的力量。|\n§. 317.\n但是就个体的整体存在是一种觉醒存在而言，个体的特殊化是年龄的自然行程。\n§. 318.\nγ）作为灵魂在自己内的反映，现实的个别性是它在封闭的、有机的肉体性内的觉醒的自为存在，是自在自为地被规定的、是尚且与躯体性同一的自我感觉，是外在的与内在的感受。\n普遍的灵魂走向还仍是直接的个别性的进程，一般而言是自然理念的进程，是从观念的普遍性向生命性的进程，这种生命性是有机的个体性。这种个体性除了它自在地在自己之内以内寓方式具有精神外，进而尚未具有什么意义，不外乎是精神个别性的和自然性的定在。但是精神因之也只还先是在外在的表象之内。因此像先前那样，有关觉醒存在作为精神的一种特殊的觉醒存在，以及年龄在精神发展独特意义上的行程方面所能更细地说到的，必须看作是被预示的或从表象中取来的。一般地说，个别性的精神与它的肉体性健全的同感共生属于前者在后者中的那种内在性的自然方面。为此所需要的不仅是上文（§. 282. ）已考察过的感官的外在感觉，而且还需要直接象征化的更确定的感觉感受，以致颜色、气味、声音直接是愉快的或讨厌的，以更为普遍或更有特质的方式存在。对于内在的共感，这里所需要的是再生系统中的一般欲望，心胸、即应激系统所在地中的愤慨和勇气，以及头脑，即感受系统所在地中的再思与精神劳作能被感受得到。\nb. 主观灵魂同其实体性的对立.\n§. 319.\n那种首先直接地在其实体同一性中生活的灵魂，在其个体性内是同自己的否定性的关联，是它的主体性同它的实体生命相对立进行分割，这种生命是不符合于灵魂的概念的。这种始初的在自己之内的反映同时也是向对方的反映，因此灵魂首先只是处于同它的自然规定性的关系之内。\n§. 320.\nα）主体处于同它的自然生命的抽象普遍性的关系之中；在这一判断中，灵魂诚然是主词，但它的宾词在这种普遍性关联内还是它的实体，它并且是一种无力的、单纯形式性的自为存在，是对它的普遍的自然生活的预感和梦想，是自然精神的感觉。\n这一关系处在精神同自己作为灵魂分程的岔路口。精神本身作为被思维的东西，即作为纯粹与自己抽象的主体性、与我性同一的东西，以普遍的东西为自己的对象，而精神与此的关联本身就是这种思维。这一更高的实体性是自由，即一切直接性的纯粹否定性。但是普遍性灵魂的实体性是直接的、仅仅肯定的同一性，不是自我意识和现实性精神所纯粹具有的自由的同一性。因此现在这一非自由的阶段是自由的自我意识的一种降级，是一种病态，在其中，按照柏拉图的想法，灵魂作为预言式的东西沉回到肝，更确切地说，作为腹部的脑沉回到神经节，而一般的精神则沉回到自然精神。这种可以作为疾病的状态表现为个别一些个人身上的巫幻关系，在历史中构成从实体的精神性向自我意识和知性东西转化的一个阶段。种种预感、预言或梦具有的许多奇异方面以及其他之类，如梦游和动物磁，都或多或少属于一般的梦这个领域，在这一领域，精神在它的自然精神和它的理性的现实之间摇摆，并在这一比自我理解的和理性的自我意识更为巨大的自然广度上将自己更为普遍的联系带给表象。不过由于真正的普遍性，即思维的普遍性只是归于理性自我意识，那种到达表象的共感生活的广袤度完全限于一个局部性范围，而且这种灵魂所看到的和预感到的，也只是自己特殊的内在性，并不是普遍本质的内在性。同样，因为灵魂已从自己自由的普遍性降到特殊性，这一巫幻的范围也是一种受约束状态，一种依存性，一种眩惑。据说在人的一种原始状态中，自然与精神不是以外在直接性的方式，而是以规律和理念的形式位于人的内在直观之前，因此，这种关于人的原始状态的观念乃是一种空洞的假设，适如在由此解释的传统状况那里已日渐共同化为更大的贫乏性一样。在这种空洞假设那里，理念的普遍的自然本性，即它作为合乎理性的思想，并没有得到重视，而这种思想只是在其自由主体性内才属于精神。\n§. 321.\nβ）但主观的灵魂本身会突破同它自然存在关系上的这种直接实体的同一性。但是，它的对立同时作为一种同一性，却乃是一种矛盾关系，是一种错乱状态。在这种状态中，由于有别的双方作为现实的东西是彼此对立的，肉体的现实就变成了灵魂的现实，反过来说也一样，灵魂就使它自己的现实成为肉体的现实。\n这种关系是一般的疯狂状态。这里需要指出的是：1）这种关系如同巫幻关系一样，都是单纯观念性环节，是非真实的关系，因而只作为状态和作为精神的疾病具有定在。这恰如一切一般地有限的东西，尤其例如形式性判断与形式性推理，都是离开真理性的，只是客观概念的抽象自在存在的环节。因此，它们只具有一种强制性的定在，这种定在以一种破坏为基础，一种在此由知性引起的破坏，因为知性把具体的东西改变成了种种抽象，并且仅仅是这种抽象的现实。这样一来，这些现在出现的关系就只是在存在中自由的精神的观念性环节，唯有这种精神才是它们的真理。它们是个体性的灵魂，因为这种灵魂是处于直言判断与假言判断的关系之内，在自己区别自身的主体性内，依然从实体上与自己的实体发生关联，而且在这种关联中本质上也是矛盾，它的存在毋宁说并不是它的存在，而是它的对方的存在。2）精神在这一关系的阶段上是被规定为一种物，确切地说，被规定为灵魂所指的那种东西。在古人那里，思维与存在的对立还不曾达到这种现实性的规定，在他们那里灵魂曾具有精神性这一较不确定的意义。反之，在近期的观念与形而上学中，精神作为一般的灵魂，则变成了一种具有许多属性和带有许多力的物，这种物进而以幽灵和天使的形式固定下来，并作为一种感性的东西，甚至还装饰上了颜色。形而上学曾坚持物这一抽象规定，因而曾使自在而自为的灵魂屈从存在的规定，质与量的规定，以及有关个别性实体、原因等反映规定。在这里，有关灵魂所在地的问题，有关这一事物与另一事物、与肉体相通的问题曾经是饶有兴味的。使形而上学摆脱作为物的精神，从而摆脱灵魂，或者同样说，使精神摆脱这种形而上学和摆脱表象观念而得以自由，并用“我”去取而代之，这必须算作康德的一项功绩。谈论作为物的精神，只能在关系范围内，也就是说，只能在反映的阶段，在这里，精神虽然使它的直接实体或它的存在的普遍性分离，并规定自己与之相判别，规定自己作为主体，但还有囿于这种存在，因而也还不曾达到它的真理性的现实。3）疯狂所表现的差异—发疯、发狂、狂暴、痴呆—是这样一些色彩层次：它们在自己彼此对立而具有的规定性上保有许多不确定的方面，就像它们本身与人们可以承认为一种健全理智状态相对立所表现出来的一样。尽管它们的判别对于这些疾病的治疗是很重要的，但如果想首先从它们当中汲取人的知识，这本身就是一种颠倒了，就像想首先从人的罪行和其他丑贱及堕落行为汲取它一样。认识那些迷误，事实上毋宁应以概念为前提，也就是说，以人应当是什么为前提。此外在所有那些形式中，疾病与其须看作是丧失理智，不如看作是疯狂意味着的东西，看作矛盾的绝对不幸，即那是主观东西与客观东西的自由同一性的精神，在它的我性中不是作为绝对的观念性，而是作为现实的物实存的，而客观的东西也正好与它对立起来实存，可它却同时又是它们的纯粹的同一性。于是，精神成了必然性的关系，或有限的交互作用的关系，直接混淆和颠倒的关系。把命运纯粹地理解为盲目的命运，即理解为与概念对立的绝对异己性，而作为这样的东西同时把它理解成终归是与自身同一的，在“一”之内把它认作它的东西和非它的东西，这就是疯狂。心散可以看作是疯狂的开始，精神在这里是在自己之内，在它的肉体性内则全然不具有现在，由于心散状态终归还是在它之内，它就把它的肉体性颠倒为它的特殊的现实，反之亦然。最高的阶段是恶意，这时自我性的单一性，即任意性，在同客观理念对立的纯粹抽象内把自己固定为一种非流动的现实，把自己和纯粹的意志混淆起来。精神心理治疗基于如下明见：疯狂无论从理智方面还是从意志方面，都不是丧失理性，而只是疯狂，因此治疗以把病人当作理性的东西为前提，并从这里取得自己能够理解病人的可靠支点。\n§. 322.\nγ）然而灵魂作为自为普遍性的概念是实体，是对另一现实性的统括力量和命运，这一现实性本质上是它自己的直接性。因此，它们在判断中的关系是扬弃这种直接性的形式，并把它设定为灵魂的形式。\n§. 323.\n因为灵魂是与这种肉体性的本原的同一性，并在其中具有它的实在性，所以，它对其进行的活动并不像对待一种外在客体那样持敌对姿态。对有机生命的一种损害和对肉体性的一种敌对的、毁坏性的处置，毋宁说会使肉体性成为一种对主体否定性的客体性，并以此使之成为一种威力和命运，而且推掉精神的立足点。\n§. 324.\n毋宁说，灵魂对肉体的活动是设定它与它的肉体性自在地存在着的同一性，这只是扬弃这种统一性的直接性形式，并作为普遍渗透的灵魂在它的肉体内成为自为的，在作为宾词的这种肉体内作为主词。|\n§. 325.\n这样灵魂就向它从自然获得的躯体（§. 318. ）内形成自己。通过重复由它的目的规定的行动，通过归纳，它在那个直接的存在内产生它的普遍性。以此，一方面，它在这种存在中内化自己，以致它与这种存在的这种同一性是由它来规定的，是它与它自己的主观统一性，另一方面，它在那种存在内具有存在；即具有这样一种存在：这种存在作为灵魂的、普遍性的存在是习惯，是特定的习惯，是熟练。作为这种由灵魂完全铸造成的工具，灵魂支配着躯体。\nc. 灵魂的现实性.\n§. 326.\n灵魂在它完全铸造成的肉体性内是作为个别性主词，而这种肉体性是作为这一主词的宾词的外在性，这一主词在其中仅仅使自己与自己关联。所以这种外在性不是表现自己，而是表现灵魂，并是灵魂的标志。作为外在东西与内在东西的这种同一性，灵魂是现实性的，并只在它的肉体性上具有它的自由形态，以及人类的、病征学和面相学的表现。\n举例言之，属于前一表现的有一般的直立形态，特别有作为绝对工具的手的发展，口的发展，笑与哭等等，以及灌注于整体的精神情调，它把身体直接宣示为一种更高自然的外在性。这种情调是一种非常虚灵的、不确定的和不可言说的变形，因为精神与它的外在性相同一则就是普遍性东西，因此在其中同样是自由的。不过，这种普遍性东西同时也具有不完善性，是一种直接而自然的东西，因而也是标志，它以此诚然表现出精神，但同时也把精神表现为一种他物，而不是像精神自为地本身作为普遍性东西那样。因此对于动物人的形态是最高的东西，正如精神对动物显示的那样。或者说，对于精神人的形态是精神的第一现象，因为人的形态是精神初始的、尚还沉于直接性领域的现实性。所以精神在它这一标志内全然是有限的精神和个别性的精神。这种标志诚然是精神的实存，但这种实存在其面相学和病征学的规定性内对于精神却是偶然的东西，想把面相学、尤其是头骨学提升为科学，这是能以有的最空虚的想头之一，如果说到从植物形态应能认识它们的治病效力，则那种空虚想法就比一纸signatura rerum［图例表］还要空虚。\n§. 327.\n物质自在自为地在作为普遍灵魂的精神中不具有什么真理性；肉体性首先不是别的，而是直接性形式，因而这种肉体性对于精神形成于肉体性之内一般而言不能作出什么阻抗。通过存在向自己之内的这种始初的形成活动，精神由于它使自己与存在相对立，扬弃了存在，并把存在规定成了它的存在，也就失去了灵魂的意义，并就是我。"}]}