{
  "bookId": "4e213cf57480",
  "title": "呻吟语",
  "author": "吕坤",
  "cover": "/api/books/4e213cf57480/image/4e213cf57480_81af629fc2.webp",
  "toc": [
    "关于本书",
    "目录",
    "序",
    "性命",
    "存心",
    "伦理",
    "谈道",
    "修身",
    "问学",
    "应务",
    "养生",
    "天地",
    "世运",
    "圣贤",
    "品藻",
    "治道",
    "人情",
    "物理",
    "广喻",
    "词章",
    "CoverPage"
  ],
  "chapterCount": 21,
  "chapterTitles": [
    "关于本书",
    "目录",
    "序",
    "性命",
    "存心",
    "伦理",
    "谈道",
    "修身",
    "问学",
    "应务",
    "养生",
    "天地",
    "世运",
    "圣贤",
    "品藻",
    "治道",
    "人情",
    "物理",
    "广喻",
    "词章",
    "CoverPage"
  ],
  "region": "东方",
  "file_type": "epub",
  "summary": "《呻吟语》是明代思想家吕坤的语录体著作，内容涵盖人生哲理、道德修养、政治见解等。吕坤以儒家思想为根基，融合道家、佛家智慧，强调内省与务实。书中语言精炼，寓意深刻，如“天地间惟理与势最尊”等句，体现其对理与势的辩证思考。该书旨在指导人们修身齐家、处世待人，被誉为“古今罕见的修身奇书”，对后世修身文化影响深远。",
  "tags": [
    "明代",
    "儒家",
    "修身"
  ],
  "rank": 27.0
}