{"title": "论残疾", "index": 774, "content": [{"type": "text", "value": "论残疾"}, {"type": "text", "value": "造物主对残疾人的确是不公平，不过这些人对待造物主亦不善，按照《圣经》所言，大部分残疾人天性多薄情寡义，这算得上是对造物主的报复。于是，他们和造物主也就扯平了。心灵和肉体当然是要契合在一起的。二者中任一个出问题，另一个也就会出问题，用拉丁语说就是：Ubi peccat in uno，periclitatur in altero。只是，“肉体”这种组织是人人必须有的，而“心灵”这个组织则是人们自由选择的。因此，有时候，“规则”和“美德”就像太阳，而人天性中的偏好或倾向就像星辰，在前者的光芒下，后者的光就会暗淡下来。所以，我们不要把“残疾”这种身体状态看作一种标志，要知道这个标志可是很容易欺骗人的。要把它看成是一种动力，这种动力在大多数情况下都会起作用。如果一个人因为身上有什么改变不了的东西而遭人歧视，他就会不断地激励自己，努力把自己从这种被轻视的状态中解救出来。从这个意义上说，所有的残疾人都是非常勇敢的。最开始的时候，他们是为了保护自己，使自己免于遭受别人的歧视。经过一段时间后，这种行为就会形成习惯。这种轻视也会促使他们变得更为勤奋，尤其是勤于观察别人的弱点，好在以后找准时机去报复这些人。残疾的身体可以消除上司的嫉妒之心，因为上司总觉得这些人并不值得重视，常常会忽视他们；残疾的身体还可以使竞争对手放松警惕，因为这些人会觉得，残疾人不可能轻易获得进步或升迁，除非他们亲眼看到这样的事实。从这一点来看，身体的残疾对于一个睿智的人倒是一个发展事业的好机会。古代的帝王比较容易宠信宦官，因为如果一个人嫉恨全世界，他反而容易对某个人尽忠职守。现在有些国家的君王也是如此。不过，这些帝王信任的是这些宦官做间谍和告密的能力，是把他们当作间谍或告密者而任用的，而不是把他们当成能力强的文职官员或官吏而任用的。残疾人也是如此。但不管怎么说，如果他们的精神世界足够强大，他们就会不遗余力地使自己摆脱被轻视的状态。他们可以通过培养美德来达到这个目的，也可以通过阴谋手段来实现。因此，如果这样的人成为伟大的领袖，你不要感到奇怪。斯巴达王阿格西劳斯、苏莱曼一世的儿子灿格 (1) 、矮小丑陋的伊索、秘鲁总督加斯卡 (2) ，就连苏格拉底 (3) 也是这样的人。"}, {"type": "text", "value": "————————————————————"}, {"type": "text", "value": "(1) Zanger，即驼背的吉汉吉尔王子，见《论王权》篇中的注释。"}, {"type": "text", "value": "(2) Gasca（1485—1567），西班牙人，1546年西班牙皇帝查理五世任命其为秘鲁总督，后归国任瓦伦西亚主教。"}, {"type": "text", "value": "(3) 这里应该说的是苏格拉底的丑陋。"}]}