{
  "title": "作为意志和表象的世界",
  "content": [
    {
      "type": "image",
      "src": "https://deepphilosophy.oss-cn-shanghai.aliyuncs.com/book_images/d0c5ade4fcbd_fd9e6dcf24.webp",
      "alt": ""
    },
    {
      "type": "text",
      "value": "经典天天读·哲学经典"
    },
    {
      "type": "text",
      "value": "作为意志和表象的世界"
    },
    {
      "type": "text",
      "value": "［德］叔本华◎著　［台］刘大悲◎译"
    },
    {
      "type": "text",
      "value": "哈尔滨出版社"
    },
    {
      "type": "text",
      "value": "黑版贸审字08-2014-085"
    },
    {
      "type": "text",
      "value": "图书在版编目（CIP）数据"
    },
    {
      "type": "text",
      "value": "作为意志和表象的世界／（德）叔本华著；刘大悲　译．—哈尔滨：哈尔滨出版社，2015.4"
    },
    {
      "type": "text",
      "value": "（经典天天读．哲学经典）"
    },
    {
      "type": "text",
      "value": "ISBN 978-7-5484-2044-6"
    },
    {
      "type": "text",
      "value": "Ⅰ．①作…　Ⅱ．①叔…②刘…　Ⅲ．①叔本华，A.（1788～1860）—哲学思想　Ⅳ．①B516.41"
    },
    {
      "type": "text",
      "value": "中国版本图书馆CIP数据核字（2014）第254602号"
    },
    {
      "type": "text",
      "value": "书　　名：作为意志和表象的世界"
    },
    {
      "type": "text",
      "value": "作　　者： ［德］叔本华　著　［台］刘大悲　译"
    },
    {
      "type": "text",
      "value": "责任编辑： 陈春林　张　薇"
    },
    {
      "type": "text",
      "value": "责任审校： 李　战"
    },
    {
      "type": "text",
      "value": "装帧设计： 回归线视觉传达"
    },
    {
      "type": "text",
      "value": "出版发行： 哈尔滨出版社（Harbin Publishing House）"
    },
    {
      "type": "text",
      "value": "社　　址： 哈尔滨市松北区世坤路738号9号楼 邮编： 150028"
    },
    {
      "type": "text",
      "value": "经　　销： 全国新华书店"
    },
    {
      "type": "text",
      "value": "印　　刷： 北京市文林印务有限公司"
    },
    {
      "type": "text",
      "value": "网　　址： www.hrbcbs.com　　www.mifengniao.com"
    },
    {
      "type": "text",
      "value": "E-mail： hrbcbs@yeah.net"
    },
    {
      "type": "text",
      "value": "编辑版权热线： （0451）87900271　87900272"
    },
    {
      "type": "text",
      "value": "邮购热线： 4006900345　（0451）87900345"
    },
    {
      "type": "text",
      "value": "销售热线： （0451）87900201　87900202　87900203"
    },
    {
      "type": "text",
      "value": "开　　本： 680mm×960mm　　1/16 印张： 19.5 字数： 270千字"
    },
    {
      "type": "text",
      "value": "版　　次： 2015年4月第1版"
    },
    {
      "type": "text",
      "value": "印　　次： 2015年4月第1次印刷"
    },
    {
      "type": "text",
      "value": "书　　号： ISBN 978-7-5484-2044-6"
    },
    {
      "type": "text",
      "value": "凡购本社图书发现印装错误，请与本社印制部联系调换。 服务热线： （0451）87900278"
    },
    {
      "type": "text",
      "value": "本社法律顾问： 黑龙江佳鹏律师事务所"
    },
    {
      "type": "text",
      "value": "目录"
    },
    {
      "type": "text",
      "value": "叔本华的生平及哲学"
    },
    {
      "type": "text",
      "value": "译者的话"
    },
    {
      "type": "text",
      "value": "英译者序言"
    },
    {
      "type": "text",
      "value": "卷一　表象世界初论"
    },
    {
      "type": "text",
      "value": "第一层面　遵循充足理由原则的表象：经验与科学的对象"
    },
    {
      "type": "text",
      "value": "卷二　意志世界初论"
    },
    {
      "type": "text",
      "value": "第一方面　意志的客观化"
    },
    {
      "type": "text",
      "value": "卷三　表象世界再论"
    },
    {
      "type": "text",
      "value": "第二层面　与充足理由原则无关的理念柏拉图的观念：艺术对象"
    },
    {
      "type": "text",
      "value": "卷四　意志世界再论"
    },
    {
      "type": "text",
      "value": "第二方面　达到自觉状态时，生命意志的肯定和否定"
    },
    {
      "type": "text",
      "value": "叔本华年谱"
    },
    {
      "type": "text",
      "value": "返回总目录"
    },
    {
      "type": "image",
      "src": "https://deepphilosophy.oss-cn-shanghai.aliyuncs.com/book_images/d0c5ade4fcbd_3f77e1e755.webp",
      "alt": ""
    },
    {
      "type": "image",
      "src": "https://deepphilosophy.oss-cn-shanghai.aliyuncs.com/book_images/d0c5ade4fcbd_620009e8a3.webp",
      "alt": ""
    },
    {
      "type": "text",
      "value": "德国哲学家叔本华（1788～1860） 叔本华思想来源之一：德国哲学家康德（1724～1804）"
    },
    {
      "type": "image",
      "src": "https://deepphilosophy.oss-cn-shanghai.aliyuncs.com/book_images/d0c5ade4fcbd_56b834994c.webp",
      "alt": ""
    },
    {
      "type": "image",
      "src": "https://deepphilosophy.oss-cn-shanghai.aliyuncs.com/book_images/d0c5ade4fcbd_894c2083d1.webp",
      "alt": ""
    },
    {
      "type": "text",
      "value": "叔本华思想来源之一：古希腊哲学家柏拉图 完成《作为意志和表象的世界》第一部时的叔本华"
    },
    {
      "type": "image",
      "src": "https://deepphilosophy.oss-cn-shanghai.aliyuncs.com/book_images/d0c5ade4fcbd_5516fefcb4.webp",
      "alt": ""
    },
    {
      "type": "image",
      "src": "https://deepphilosophy.oss-cn-shanghai.aliyuncs.com/book_images/d0c5ade4fcbd_97e96d5a7a.webp",
      "alt": ""
    },
    {
      "type": "text",
      "value": "印度教创造之神：梵天。叔本华用之比喻他哲学思想的“理智”概念 印度教毁灭之神：湿婆。叔本华用之比喻他哲学思想的“意志”概念"
    },
    {
      "type": "image",
      "src": "https://deepphilosophy.oss-cn-shanghai.aliyuncs.com/book_images/d0c5ade4fcbd_c8ed917576.webp",
      "alt": ""
    },
    {
      "type": "text",
      "value": "印度教守护之神：毗湿奴。叔本华用之比喻他哲学思想的“表象”概念"
    }
  ],
  "index": 55
}