{"title": "章一", "index": 426, "content": [{"type": "text", "value": "章一"}, {"type": "text", "value": "凡所见之城邦皆为某种共同体，而一切共同体之建立皆是为了某类善业。人类的所有行为即是为了得到心中的善。既然所有共同体都以此为目的，那么代表最高、涵盖最广的社会政治共同体所追求的一定是至善。"}, {"type": "text", "value": "有人认为无论政客、君王、家主还是主人都一样。他们只是在管理人数的多寡上有区别，在性质上却相同。譬如，管几个人的叫主人；再多点的叫家主；而治理大量人口的则称为政客或君王。这样看起来似乎名门望族与寡民小国之间毫无差别。政客与君王的区别也仅是如此：君王以个人名义统治全国；政客凭政治科学规章制度轮流执政。"}, {"type": "text", "value": "实际上，这些观点都是错的，运用一直以来的分析方法加以考察，人们便会明白。正如在其他学科上，组合物总会被拆解为构成它的最小单位。因此，在政治学上，我们也要找到组成城邦的基本要素，由此分析各处不同，试图得出有力论断。"}]}