{"bookId": "21a479c4978d", "title": "道德情操论", "author": "亚当·斯密", "cover": "/api/books/21a479c4978d/image/21a479c4978d_a87393bd85.webp", "toc": ["前折页", "书名页", "版权页", "目录", "译者序", "告读者", "第一篇　论行为的合宜性", "第一章　论合宜感", "第一节　同情感", "第二节　论彼此同情的快感", "第三节　论通过他人的情感与我们的是否相合来评论他人的情感合宜与否的方式", "第四节　续前节", "第五节　论可亲与可敬的美德", "第二章　论各种感情合宜的程度", "引言", "第一节　论源自身体的感情", "第二节　论源自特殊的想象偏向或习性的感情", "第三节　论不和乐的感情", "第四节　论和乐的感情", "第五节　论自爱的感情", "第三章　论处境的顺逆对人类评论行为合宜与否的影响", "第一节　虽然我们对悲伤的同情感通常比对快乐的同情感更为强烈，但悲伤的同情感通常远远不如主要当事人自然感觉到的悲伤那般强烈", "第二节　论雄心壮志的根源以及地位差别", "第三节　论钦佩富贵与藐视贫贱的心理倾向腐化我们的道德判断", "第二篇　论功劳与过失，即论奖赏与惩罚的对象", "第一章　论功过感", "引言", "第一节　凡是看起来当受感激的对象，似乎都该奖赏；同样的，凡是看起来当受怨恨的对象，似乎都该受惩罚", "第二节　论当受感激与怨恨的对象", "第三节　如果施惠者的行为未获赞许，则受惠者的感激便很少会有人同情；相反，如果加害者的动机未受谴责，则受害者的怨恨便不会有人同情", "第四节　前几节的要点重述", "第五节　功过感的分析", "第二章　论正义与仁慈", "第一节　这两种美德的比较", "第二节　论正义感、自责感，并论功劳感", "第三节　论自然女神赋予心灵这种构造的效用", "第三章　论运气如何影响人类对于行为功过的感觉", "引言", "第一节　论运气所以有这种影响的原因", "第二节　论运气的这种影响的程度", "第三节　论这种感觉出轨的终极原因", "第三篇　论我们品评自己情感与行为的基础，并论义务感", "第一节　论自许与自责的原理", "第二节　论喜欢受到赞美及喜欢值得赞美；并论害怕受到谴责及害怕应受谴责", "第三节　论良心的影响与权威", "第四节　论自欺的性质，并论概括性规则的起源与应用", "第五节　论概括性道德规则的影响与权威，以及这些规则应当被视为神的法律", "第六节　在哪些情况下，义务感应当是我们唯一的行为原则，以及在哪些情况下，它应当获得其他动机的赞许", "第四篇　论效用对赞许感的影响", "第一节　论合用的外表赋予所有工艺品的美，并论这种美的广泛影响", "第二节　论合用的外表赋予人的性格与行为的美，并论这种美在何等程度内可以被视为赞许该性格或行为的一个根本要素", "第五篇　论社会习惯与时尚对道德赞许与谴责等情感的影响", "第一节　论社会习惯与时尚对美丑概念的影响", "第二节　论社会习惯与时尚对道德情感的影响", "第六篇　论好品格", "引言", "第一章　论个人的性格中影响其自身幸福的那一面，或论审慎", "第二章　论个人的性格中影响他人幸福的那一面", "引言", "第一节　论自然女神按何种顺序把哪些个人托付给我们照顾", "第二节　论自然女神按何种顺序把哪些社会团体托付给我们帮助", "第三节　论博爱", "第三章　论克己", "结论", "第七篇　论道德哲学体系", "第一章　论道德情感的理论应该探讨的问题", "第二章　论各种说明美德之性质的学说", "引言", "第一节　论主张美德以合宜为本的学说", "第二节　论主张美德以审慎为本的学说", "第三节　论主张美德以慈善为本的学说", "第四节　论善恶不分的学说", "第三章　论各种关于赞许之原理的学说", "引言", "第一节　论主张赞许之原理本于自爱的学说", "第二节　论主张赞许之原理本于理性的学说", "第三节　论主张赞许之原理本于感觉的学说", "第四章　论不同的作者处理道德实务规则的方式", "后折页"], "chapterCount": 28, "chapterTitles": ["part0000", "温家宝总理五次推荐大师巨著", "part0003", "目　录Contents", "译者序", "告读者(1)", "第一篇　论行为的合宜性", "第一章　论合宜感", "第二章　论各种感情合宜的程度", "第三章　论处境的顺逆对人类评论行为合宜与否的影响", "第二篇　论功劳与过失，即论奖赏与惩罚的对象", "第一章　论功过感", "第二章　论正义与仁慈", "第三章　论运气如何影响人类对于行为功过的感觉", "第三篇　论我们品评自己情感与行为的基础，并论义务感", "第四篇　论效用对赞许感的影响", "第五篇　论社会习惯与时尚对道德赞许与谴责等情感的影响", "第六篇　论好品格", "引　言", "第二章　论个人的性格中影响他人幸福的那一面", "第三章　论克己", "结　论", "第七篇　论道德哲学体系", "第一章　论道德情感的理论应该探讨的问题", "第二章　论各种说明美德之性质的学说", "第三章　论各种关于赞许之原理的学说", "第四章　论不同的作者处理道德实务规则的方式", "part0028"], "region": "西方", "file_type": "epub", "summary": "《道德情操论》是亚当·斯密在1759年出版的一部伦理学著作，系统探讨了人类道德情感的起源与本质。斯密的核心思想是“同情”——即我们能够通过想象进入他人的处境，从而产生情感共鸣。他认为，道德判断的基础不是抽象的理性原则，而是这种基于同情的“公正的旁观者”视角。当我们做出道德评价时，实际上是在想象一个不偏不倚的旁观者会如何看待我们的行为。这一理论不仅深刻解释了道德感的形成机制，也奠定了斯密在启蒙运动中的哲学地位。值得注意的是，斯密后来在《国富论》中探讨经济行为时，并没有抛弃《道德情操论》中的伦理关怀；相反，他认为市场经济的正常运行需要以道德情感为基础。这两部著作共同构成了斯密对人类社会完整而统一的理解。《道德情操论》对后世伦理学、心理学乃至经济学都产生了深远影响，是研究道德哲学与社会科学交叉领域的经典文本。", "tags": ["伦理学", "启蒙运动", "苏格兰启蒙运动"]}