{"bookId": "343df8697039", "title": "陀思妥耶夫斯基集（全九册）", "author": "费奥多尔·陀思妥耶夫斯基", "cover": "/api/books/343df8697039/image/343df8697039_a459ccbe53.webp", "toc": ["版权信息", "罪与罚", "版权信息", "“世界名著名译文库”总序", "陀思妥耶夫斯基其人其书", "“我只要一张口，到处便会议论纷纷”", "苦役犯与《死屋手记》", "嗜赌如命与没命地写作", "传世之作《罪与罚》与《卡拉马佐夫兄弟》", "复调特征及作家的艺术观", "一部俄罗斯式的新长篇小说——《罪与罚》译序", "第一章", "一", "二", "三", "四", "五", "六", "七", "第二章", "一", "二", "三", "四", "五", "六", "七", "第三章", "一", "二", "三", "四", "五", "六", "第四章", "一", "二", "三", "四", "五", "六", "第五章", "一", "二", "三", "四", "五", "第六章", "一", "二", "三", "四", "五", "六", "七", "八", "尾?声", "一", "二", "附录 陀思妥耶夫斯基生平及创作年表435", "白痴", "版权信息", "“世界名著名译文库”总序", "说不尽的陀思妥耶夫斯基", "一", "二", "三", "第一部", "一", "二", "三", "四", "五", "六", "七", "八", "九", "十", "十一", "十三", "十四", "十五", "十六", "第二部", "一", "二", "三", "四", "五", "六", "七", "八", "九", "十", "十一", "十二", "第三部", "一", "二", "三", "四", "五", "六", "七", "八", "九", "十", "第四部", "一", "二", "三", "四", "五", "六", "七", "八", "九", "十", "十一", "十二 结束语", "群魔", "版权信息", "“世界名著名译文库”总序", "译本序 人的灵魂的伟大审问者", "第一部", "第一章 （代引言）", "一", "二", "三", "四", "五", "六", "七", "八", "九", "第二章 哈利太子90。提亲", "一", "二", "三", "四", "五", "六", "七", "八", "第三章 别人的罪孽", "一", "二", "三", "四", "五", "六", "七", "八", "九", "十", "第四章 瘸腿女人", "一", "二", "三", "四", "五", "六", "七", "第五章 绝顶聪明的毒蛇", "一", "二", "三", "四", "五", "六", "七", "八", "第二部", "第一章 夜", "一", "二", "三", "四", "五", "六", "七", "第二章 夜（续）", "一", "二", "三", "四", "第三章 决斗", "一", "二", "三", "四", "第四章 大家都翘首以待", "一", "二", "三", "第五章 游艺会之前", "一", "二", "三", "第六章 彼得·斯捷潘诺维奇到处奔忙", "一", "二", "三", "四", "五", "六", "七", "第七章 在我们的人那里", "一", "二", "第八章 伊万王子", "第九章 斯捷潘·特罗菲莫维奇被抄家", "第十章 海盗。不祥的上午", "一", "二", "三", "第三部", "第一章 游艺会。第一部分", "一", "二", "三", "四", "第二章 游艺会的结局", "一", "二", "三", "四", "第三章 头号绯闻", "一", "二", "三", "第四章 最后的决定", "一", "二", "三", "四", "第五章 女旅客", "一", "二", "三", "四", "五", "六", "第六章 费尽心机的一夜", "一", "二", "三", "第七章 斯捷潘·特罗菲莫维奇的最后漂泊", "一", "二", "三", "第八章 结尾", "附录", "第九章 在吉洪的修道室797", "一", "二", "三", "译后记", "卡拉马佐夫兄弟", "版权信息", "“世界名著名译文库”总序", "译本序", "作者的话", "第一部", "第一卷 一个家庭的历史", "一 费奥多尔·巴夫洛维奇·卡拉马佐夫", "二 打发长子", "三 第二次结婚以及第二个妻子生的两个孩子", "四 第三个儿子阿廖沙", "五 长老们", "第二卷 不合时宜的聚会", "一 来到修道院", "二 老丑角", "三 虔诚的乡下女人", "四 信仰不坚的太太", "五 必定如此，必定如此", "六 这种人活着有什么用！", "七 野心勃勃的神学校学生", "八 争吵", "第三卷 好色之徒", "一 在仆人房里", "二 丽萨维塔·斯梅尔佳夏娅", "三 一颗火热的心在忏悔（诗歌）", "四 一颗火热的心在忏悔（故事）", "五 一颗火热的心在忏悔（“脚跟朝上”）", "六 斯梅尔佳科夫", "七 争论", "八 喝白兰地的时候", "九 色鬼", "十 两个女人在一起", "十一 又一个丧失了名誉的人", "第二部", "第一卷 折磨", "一 费拉蓬特神甫", "二 在父亲家里", "三 和小学生们相遇", "四 在霍赫拉科娃家", "五 客厅里的折磨", "六 小木屋里的折磨", "七 空气清新的室外", "第二卷 赞成与反对", "一 婚约", "二 斯梅尔佳科夫弹吉他", "三 兄弟俩互相了解", "四 叛逆", "五 宗教大法官", "六 暂时还很不清楚的一章", "七 “跟聪明人谈谈也是有趣的”", "第三卷 俄罗斯教士", "一 佐西马长老和他的客人们", "二 已故司祭佐西马长老的生平（传略），阿列克谢·费奥多罗维奇·卡拉马佐夫根据他的自述编写", "三 佐西马长老谈话和训言摘录", "第三部", "第一卷 阿廖沙", "一 腐臭的气味", "二 那样的时刻", "三 一根葱", "四 加利利的伽拿128", "第二卷 米佳", "一 库兹马·萨姆索诺夫", "二 “猎狗”", "三 金矿", "四 在黑暗中", "五 突然的决定", "六 我亲自来了", "七 无可争议的旧恋人", "八 梦呓", "第三卷 预审", "一 佩尔霍金交上官运", "二 报警", "三 灵魂磨难155的历程。第一次磨难", "四 第二次磨难", "五 第三次磨难", "六 检察官捉住了米佳", "七 米佳的重大秘密", "八 证人的证词。婴儿", "九 米佳被带走了", "第四部", "第一卷 男孩子们", "一 科利亚·克拉索特金", "二 孩子们", "三 一个小学生", "四 茹奇卡", "五 在伊柳沙的病榻旁", "六 早熟", "七 伊柳沙", "第二卷 伊凡·费奥多罗维奇哥哥", "一 在格鲁申卡家里", "二 一条病腿", "三 小魔鬼", "四 颂歌和秘密", "五 不是你，不是你", "六 与斯梅尔佳科夫的第一次会面", "七 第二次走访斯梅尔佳科夫", "八 第三次，也是最后一次走访斯梅尔佳科夫", "九 魔鬼。伊凡·费奥多罗维奇的噩梦", "十 “这是他说的”", "第三卷 错误的审判", "一 致命的一天", "二 危险的证人", "三 医学鉴定和一磅胡桃", "四 幸福向米佳微笑", "五 突如其来的灾难", "六 检察官的演说。性格分析", "七 历史的回顾", "八 关于斯梅尔佳科夫的专题研究", "九 淋漓尽致的心理分析。飞奔的三驾马车。检察官演说的结尾", "十 律师的演说。两头都能打人的大棒", "十一 不存在这笔钱。也没有发生抢劫的事", "十二 也没有发生谋杀", "十三 诲淫诲盗的评论家", "十四 庄稼汉固执己见", "尾声", "一 营救米佳的计划", "二 谎言一时成了真理", "三 伊柳沙的葬礼。巨石旁的演说", "附录 陀思妥耶夫斯基关于《卡拉马佐夫兄弟》的论述", "被侮辱与被损害的", "版权信息", "“世界名著名译文库”总序", "译本序：阴霾天空下的悲惨故事", "第一部", "第一章", "第二章", "第三章", "第四章", "第五章", "第六章", "第七章", "第八章", "第九章", "第十章", "第十一章", "第十二章", "第十三章", "第十四章", "第十五章", "第二部", "第一章", "第二章", "第三章", "第四章", "第五章", "第六章", "第七章", "第八章", "第九章", "第十章", "第十一章", "第三部", "第一章", "第二章", "第三章", "第四章", "第五章", "第六章", "第七章", "第八章", "第九章", "第十章", "第四部", "第一章", "第二章", "第三章", "第四章", "第五章", "第六章", "第七章", "第八章", "第九章", "尾声 最后的回忆", "译后记", "再版译后记", "少年", "版权信息", "“世界名著名译文库”总序", "译本序地下室·双重人格·地下室诗人", "第一部", "第一章", "一", "二", "三", "四", "五", "六", "七", "八", "第二章", "一", "二", "三", "四", "第三章", "一", "二", "三", "四", "五", "六", "第四章", "一", "四", "三", "四", "第五章", "一", "二", "三", "四", "第六章", "一", "二", "三", "四", "第七章", "一", "二", "三", "四", "第八章", "一", "二", "三", "第九章", "一", "二", "三", "四", "五", "第十章", "一", "二", "三", "四", "五", "第二部", "第一章", "一", "二", "三", "四", "第二章", "一", "二", "三", "第三章", "一", "二", "三", "四", "第四章", "一", "二", "第五章", "一", "二", "三", "第六章", "一", "二", "三", "四", "第七章", "一", "二", "三", "第八章", "一", "二", "三", "四", "五", "六", "第九章", "一", "二", "三", "四", "第三部", "第一章", "一", "二", "三", "第二章", "一", "二", "三", "四", "五", "第三章", "一", "二", "三", "四", "第四章", "一", "二", "三", "四", "第五章", "一", "二", "三", "第六章", "一", "二", "三", "第七章", "一", "二", "三", "第八章", "一", "二", "第九章", "一", "二", "三", "四", "五", "第十章", "一", "二", "三", "四", "第十一章", "一", "二", "三", "四", "第十二章", "一", "二", "三", "四", "五", "第十三章", "结尾", "一", "二", "三", "附录", "前言草", "地下室手记：陀思妥耶夫斯基中篇小说选", "版权信息", "“世界名著名译文库”总序", "译本序 用灵活多样的形式探索复杂的人性", "穷人", "白夜49——录自一个幻想者的回忆", "斯捷潘齐科沃村的居民——摘自一个无名氏的回忆录", "第一部", "第二部，也是最后一部", "地下室手记", "第一章 地下室201", "第二章 湿雪纷飞230", "鳄鱼——一桩非常事件，或称游廊市场268上发生的怪事"], "chapterCount": 279, "chapterTitles": ["版权信息", "第3章", "罪与罚", "版权信息", "第6章", "“世界名著名译文库”总序", "陀思妥耶夫斯基其人其书", "“我只要一张口，到处便会议论纷纷”", "苦役犯与《死屋手记》", "嗜赌如命与没命地写作", "传世之作《罪与罚》与《卡拉马佐夫兄弟》", "复调特征及作家的艺术观", "一部俄罗斯式的新长篇小说——《罪与罚》译序", "第一章", "二", "三", "四", "五", "六", "七", "第二章", "二", "三", "四", "五", "六", "七", "第三章", "二", "三", "四", "五", "六", "第四章", "二", "三", "四", "五", "六", "第五章", "二", "三", "四", "五", "第六章", "二", "三", "四", "五", "六", "七", "八", "尾?声", "二", "附录　陀思妥耶夫斯基生平及创作年表435", "第57章", "白痴", "版权信息", "第60章", "“世界名著名译文库”总序", "说不尽的陀思妥耶夫斯基", "一", "二", "三", "第一部", "二", "三", "四", "五", "六", "七", "八", "九", "十", "十一", "十三", "十四", "十五", "十六", "第二部", "二", "三", "四", "五", "六", "七", "八", "九", "十", "十一", "十二", "第三部", "二", "三", "四", "五", "六", "七", "八", "九", "十", "第四部", "二", "三", "四", "五", "六", "七", "八", "九", "十", "十一", "十二　结束语", "第115章", "群魔", "版权信息", "第118章", "“世界名著名译文库”总序", "译本序　人的灵魂的伟大审问者", "第一部", "第二章　哈利太子90。提亲", "第三章　别人的罪孽", "第四章　瘸腿女人", "第五章　绝顶聪明的毒蛇", "第二部", "第二章　夜（续）", "第三章　决斗", "第四章　大家都翘首以待", "第六章　彼得·斯捷潘诺维奇到处奔忙", "第七章　在我们的人那里", "第八章　伊万王子", "第九章　斯捷潘·特罗菲莫维奇被抄家", "第十章　海盗。不祥的上午", "第三部", "第二章　游艺会的结局", "第三章　头号绯闻", "第四章　最后的决定", "第五章　女旅客", "第六章　费尽心机的一夜", "第七章　斯捷潘·特罗菲莫维奇的最后漂泊", "第八章　结尾", "附录", "译后记", "第145章", "卡拉马佐夫兄弟", "版权信息", "第148章", "“世界名著名译文库”总序", "译本序", "作者的话", "第一部", "第二卷　不合时宜的聚会", "第三卷　好色之徒", "第二部", "第二卷　赞成与反对", "第三卷　俄罗斯教士", "第三部", "第二卷　米佳", "第三卷　预审", "第四部", "第二卷　伊凡·费奥多罗维奇哥哥", "五　不是你，不是你", "第三卷　错误的审判", "七　历史的回顾", "尾声", "二　谎言一时成了真理", "三　伊柳沙的葬礼。巨石旁的演说", "附录　陀思妥耶夫斯基关于《卡拉马佐夫兄弟》的论述", "第170章", "被侮辱与被损害的", "版权信息", "第173章", "“世界名著名译文库”总序", "译本序：阴霾天空下的悲惨故事", "第一部", "第二章", "第三章", "第四章", "第五章", "第六章", "第七章", "第八章", "第九章", "第十章", "第十一章", "第十二章", "第十三章", "第十四章", "第十五章", "第二部", "第二章", "第三章", "第四章", "第五章", "第六章", "第七章", "第八章", "第九章", "第十章", "第十一章", "第三部", "第二章", "第三章", "第四章", "第五章", "第六章", "第七章", "第八章", "第九章", "第十章", "第四部", "第二章", "第三章", "第四章", "第五章", "第六章", "第七章", "第八章", "第九章", "尾声　最后的回忆", "译后记", "再版译后记", "第224章", "少年", "版权信息", "第227章", "“世界名著名译文库”总序", "译本序地下室·双重人格·地下室诗人", "第一部", "第二章", "第三章", "第四章", "第五章", "第六章", "第七章", "第八章", "第九章", "第十章", "第二部", "第二章", "第三章", "第四章", "第五章", "第六章", "第七章", "第八章", "第九章", "第三部", "第二章", "第三章", "第四章", "第五章", "第六章", "第七章", "第八章", "第九章", "第十章", "第十一章", "第十二章", "第十三章", "附录", "第263章", "地下室手记：陀思妥耶夫斯基中篇小说选", "版权信息", "第266章", "“世界名著名译文库”总序", "译本序　用灵活多样的形式探索复杂的人性", "穷人", "第270章", "白夜49——录自一个幻想者的回忆", "斯捷潘齐科沃村的居民——摘自一个无名氏的回忆录", "第一部", "第274章", "第二部，也是最后一部", "地下室手记", "第一章　地下室201", "第二章　湿雪纷飞230", "鳄鱼——一桩非常事件，或称游廊市场268上发生的怪事", "第280章"], "region": "西方", "file_type": "epub", "summary": "这部九卷本《陀思妥耶夫斯基集》系统收录了陀思妥耶夫斯基的主要文学作品、日记及书信，是研究这位俄罗斯文学巨匠思想全貌的权威文本。陀思妥耶夫斯基的创作围绕自由、信仰、理性与非理性的冲突等核心主题展开，通过《罪与罚》《卡拉马佐夫兄弟》《地下室手记》等杰作，深刻剖析了现代人在虚无与神性之间的挣扎。他批判理性主义对人性的简化，揭示非理性、痛苦和自由意志在人类存在中的根本地位；他通过“地下室人”等角色对现代人异化状态的哲学反思，成为20世纪存在主义哲学与文学对话的重要源泉。文集中的日记和书信则直接呈现了陀思妥耶斯基本人对宗教、政治、伦理问题的独立思考，尤其是他对“美拯救世界”这一信念的坚持。陀思妥耶夫斯基的思想对尼采、萨特、加缪、弗洛伊德等思想家产生了深远影响，其作品中关于自由、责任和苦难救赎的探讨，至今仍是哲学和文学领域不可回避的经典命题。这套文集不仅是文学爱好者的必备藏书，更是理解现代性精神危机和人类生存困境的重要哲学文献。", "tags": ["存在主义", "伦理学", "宗教哲学"]}