{"bookId": "e2a4c4f78c40", "title": "现象学的观念", "author": "埃德蒙德·胡塞尔", "cover": null, "toc": [], "chapterCount": 0, "chapterTitles": [], "region": "西方", "file_type": "pdf", "summary": "《现象学的观念》是埃德蒙德·胡塞尔现象学方法的奠基性著作，核心主题在于通过“现象学还原”悬置自然态度，将意识本身及其意向性结构确立为绝对明证性的领域。胡塞尔认为，传统哲学陷入心理主义与自然主义的困境，而现象学还原能够帮助我们回到“事物本身”，即意识如何构造对象的意义。该书首次系统阐明了现象学作为严格科学的方法论基础，区分了心理现象与纯粹意识，强调意向性——即意识总是关于某物的意识——作为哲学分析的起点。历史地位上，这本书开启了现象学运动，为后来的“生活世界”与“主体间性”理论开辟了道路，深刻影响了海德格尔、萨特、梅洛-庞蒂等思想家。核心概念包括“现象学还原”“意向性”“本质直观”“纯粹意识”等。胡塞尔主张，通过悬置对存在世界的自然信念，我们可以获得一个绝对自明的意识领域，从而为知识奠定坚实基础。这本书适合想了解现象学入门方法、意识哲学与认识论基础的读者。", "tags": ["现象学"]}