{"bookId": "0c6979bc7b9d", "title": "家庭、私有制和国家的起源", "author": "弗里德里希·恩格斯", "cover": "/api/books/0c6979bc7b9d/image/0c6979bc7b9d_2a623fd26c.webp", "toc": ["1884年第一版序言", "1891年第四版序言2", "一 史前各文化阶段", "二 家庭", "三 易洛魁人的氏族", "四 希腊人的氏族", "五 雅典国家的产生", "六 罗马的氏族和国家", "七 克尔特人和德意志人92的氏族93", "八 德意志人国家的形成", "九 野蛮时代和文明时代"], "chapterCount": 11, "chapterTitles": ["1884年第一版序言", "1891年第四版序言2", "一 史前各文化阶段", "二 家庭", "三 易洛魁人的氏族", "四 希腊人的氏族", "五 雅典国家的产生", "六 罗马的氏族和国家", "七 克尔特人和德意志人92的氏族93", "八 德意志人国家的形成", "九 野蛮时代和文明时代"], "region": "西方", "file_type": "epub", "summary": "《家庭、私有制和国家的起源》是恩格斯晚年运用历史唯物主义方法写成的重要著作，1884年首次出版。本书以摩尔根的人类学研究成果为基础，系统探讨了家庭形态从群婚制到一夫一妻制的演变过程，分析了私有制如何在这一过程中逐渐产生并巩固。恩格斯指出，原始社会以母权制氏族为基础，财产公有，社会平等；但随着生产力的发展，剩余产品出现，私有制随之产生，导致阶级分化。为了维护私有制和阶级统治，国家应运而生——它本质上是一个阶级压迫另一个阶级的工具。恩格斯通过对古希腊、罗马和日耳曼社会的分析，揭示了国家起源的普遍规律。他预言，随着生产力的高度发展和阶级的最终消失，国家也将“自行消亡”，回归到“自由人联合体”的社会形态。该书不仅是对摩尔根理论的马克思主义改造，更是对历史唯物主义的经典应用，为理解社会制度的演变提供了科学框架。尽管后来的人类学发现对摩尔根的部分结论提出了修正，但恩格斯对私有制与国家关系的分析仍然具有深刻的现实意义。", "tags": ["马克思主义哲学", "政治哲学", "历史唯物主义", "西方哲学"]}