{"title": "第九卷", "index": 431, "content": [{"type": "text", "value": "第九卷\n苏：“最后就轮到僭主政治的个人了。对于这些人我们已经问过，他是如何从民主政治形成的呢？他又是如何生活，是幸福还是痛苦呢？”\n“是的，”他说，“最后剩下来的问题就是他了。”\n“但是，”我说，“在这之前还有一个问题留待回答。”\n阿：“什么问题？”\n苏：“我认为我们还没有充分地给欲望的性质和种类下好定义。只有回答了这个问题，我们的提问才不至于迷离不清。”\n“好的，”他说，“亡羊补牢，为时不晚。”\n“非常正确，”我说，“现在来看看我想要理解的这个点。我当然会认为那些不必要的愉悦和欲望是非法的。每个人似乎都想要这些愉悦和欲望，但是有些人可以受到法律和理性的控制，存在于他们心中的是一些更好的欲望。这些欲望要不就被全部禁止，要不就变得十分虚弱，而在其他情况下它们会变得更强壮、更多。”\n阿：“你说的欲望是哪一种？”\n苏：“我说的是当人们已经睡醒，而理性和人类控制的力量还在沉睡之时的欲望。我们内心的野兽开始暴殄天物，摆脱掉睡意，出发去满足他的欲望。这时就没有什么愚蠢之事和罪行做不出来了——乱伦和其他不正常的结合，或者是杀亲，或者是吃禁止食用的食物。——其实如果他们有害羞心和理智的话，就不会做这些坏事的。”\n“就是那样的。”他说。\n苏：“但是如果一个人脾性健康有节制，就算在睡眠的时候他也会唤醒他的理性力量，用高贵的思想和质问来滋养这份力量，让自己陷入冥想。对于他的欲望，他没有过度放任也没有过度忽视，而是让它们沉静下来，并且阻止自己的愉悦和痛苦来打扰更高的原则。他只留下了这个原则的纯粹的抽象物，自由地思考，可从未知得到已知，不管是在过去、现在还是未来。如果他在再次减轻了激动的元素的时候和别人争吵，我的意思是，当他使两种不理性的原则冷静下来的时候，他会在他休息之前叫醒第三种原则，也就是理性，你知道，那样他就离真理更近了，是最不容易游戏人生的。”\n阿：“我完全同意。”\n苏：“我说的这些已经开始离题了。但是我想关注的那个点实际上我们都有。哪怕是在好人身上，也会有非法的野兽的一面，这一面会在人们沉睡时若隐若现。请神保佑，假设我是对的，你会同意我的说法。”\n阿：“好的，我同意。”\n苏：“现在想一想我们所认为的民主人士的特点吧。他从小就被吝啬的父母养育，他的父亲培养了他的节省的习惯。他不赞成那些不必要的欲望，也就是各种娱乐和装饰是吗？”\n阿：“没错。”\n苏：“但是后来他与那些精明放纵之人为伍，堕落入他们的荒唐人生，开始厌恶他父亲的生活方式。到最后，由于他又比腐蚀他的那些人要好一些，于是他便转变方向，走向了这两派的中间道路，既不太粗俗，也不太具有奴性，而是过着一种有节制的享受娱乐的生活。这样他便摒弃了寡头者的身份，成为了一个民主派？”\n“是的，”他说，“这就是我们对他的看法，现在还是这样看。”\n“现在，”我说，“许多年过去了，你必须想象这样的一个人也有了儿子，而且是按照他这个父亲的原则带大的。”\n阿：“我可以想象。”\n苏：“你还得想象曾经发生在这位父亲身上的事现在又发生在了他的儿子身上。他过着无法无天的生活，诱惑他的那些人说这是完美的自由。而他的父亲和父亲的朋友却支持他的节制的欲望，另一个派别支持另一类欲望。一旦这些可怕的魔术师和僭主的制造者发现他们失去了他的支持，他们就会图谋在他身上植入一种能起主宰作用的激情，来向他的空虚和挥霍的欲望作威作福，就像一只巨大有翼的雄蜂那样。这是我能想到的最能描绘他的形象的比喻了。”\n“是的，”他说，“这是最合适的比喻。”\n苏：“当他一味贪求其他事物，比如成堆的香水、花环和美酒以及放荡生活的各种娱乐，并让这些事物围绕在他周围的时候，被推到风口浪尖上的那个欲望就会被充分滋养，并且被植入他的雄蜂一样的本性里面。于是到最后，他的灵魂的贪求就会和他的护卫一起疯狂起来，爆发成一场狂怒。如果他发现自己身上还生成着什么好的想法和欲望，或者还残留下什么羞耻之心，他就会终结这些好的原则，把它们驱逐出去，直到将节制一扫而尽，让疯狂发挥到极致为止。”\n“是的，”他说，“这就是僭主式人物产生的方式。”\n苏：“这难道不也是自古以来爱情被叫作专制暴君的原因吗？”\n阿：“我没有理由怀疑。”\n“另外，”我说，“醉酒的人不也有点儿暴君脾气吗？”\n阿：“有的。”\n苏：“你知道一个精神错乱的人会幻想他是绝对的统治者，不仅可以统管人类，还能管到神的头上？”\n阿：“会那样的。”\n苏：“而人一旦成为名副其实的僭主暴君，不管是天性使然还是习惯使然，还是凭借着这二者的合力作用，他都会变成醉鬼，富有贪欲，并且容易被激怒不是吗？噢，我的朋友，是那样的吗？”\n阿：“显然是的。”\n苏：“他们的表现和起源就是这样的。那么，他会如何生活呢？”\n阿：“哎哟，还是你来告诉我吧。”\n“我认为，”我说，“他下一步要做的就是享受盛宴，尽情喝酒狂欢，在高级妓女中间周旋，做等等之类的事情。他的心灵被激情占据，灵魂也被完全支配。”\n阿：“那是当然的。”\n苏：“是的。越来越多的欲望没日没夜地在他心里生长出来，而且变得越来越强大，这些欲望也就需要更多的东西来满足它们了。”\n“就是那样的。”他说。\n苏：“如果他有一些收入的话，他就会马上花掉。”\n阿：“没错。”\n苏：“于是他便开始借债，财产越来越少。”\n阿：“当然。”\n苏：“当他一无所有的时候，他的那些欲望难道不会像乌鸦巢里的小乌鸦那样吵着要食物吗？而他也被这些欲望刺激了，出于对自己的爱开始狂怒，不得不去欺骗和剥夺他人的财产，来满足自己吗？”\n阿：“是的，应该就是那样的。”\n苏：“如果他想要远离痛苦折磨的话，他就一定会想方设法地拥有金钱。”\n阿：“他一定会的。”\n苏：“他的内心有一系列的愉悦，新的不停占据旧的，而年轻的他一定会比他的父亲和母亲拥有得更多。如果他花掉了自己的财产，他就会攫取他的父母的财产。”\n阿：“毫无疑问他会那样的。”\n苏：“如果他的父母不愿意给，那样他就会首先尝试欺骗他们。”\n阿：“非常正确。”\n苏：“如果他失败了，那么他就会采用暴力，抢夺他们的财产。”\n阿：“是的，很有可能。”\n苏：“如果这两位老人奋力抗争，会发生什么事情呢，我的朋友？这个人会不择手段采取暴力形式吗？”\n“天哪，”他说，“我不得不替他的父母感到难过。”\n苏：“但是，我的天哪！阿德曼图斯，如果为了新流行的对娼妓的爱恋，而这娼妓只不过是一种必要的联系，你会不会相信他会鞭打曾是他的好友并且生育他的母亲，把娼妓带来和他住在一起，让母亲屈居于娼妓之下？或者，在类似的情况下，为了其他可有可无的欲望，年轻人对自己憔悴的父亲做出同样的事情，而他的父亲曾是他最好最不可缺少的朋友？”\n“是的，”他说，“我相信他会那样做的。”\n“那么，”我说，“僭主暴君有这样的父母看来是很幸运了。”\n“他是很幸运。”他答道。\n苏：“他首先攫取了父母的财产，挥霍干净以后，他的灵魂里面已经充满了愉悦。于是他闯入他人房屋，或者去抢劫那些夜归人，然后便开始洗劫神庙。同时，他小的时候还抱有的那些想法，那些教他判断是非黑白的想法，都被新解放的想法所淹没了，成为了他的护卫，分享着他的帝国。在民主的日子里，他还服从于法律和他的父亲，只有在进入梦境的时候才会放纵自己。但是现在，他被激情所主宰，他的状态变成了以前只有在睡梦中才会释放出的那种状态。他开始犯邪恶的罪，或偷吃被禁止的食物，或者做出其他恐怖的事情。激情成为了他的暴君，虽然非法，却堂而皇之地占据着他的心灵，做他的国王，带领他前进，就像一个僭主带领一个国家那样，做出许许多多鲁莽的行为，来维护他自己和他的那帮乌合之众。其实也正是这些乌合之众把他从外面带到道上，或者是他自己让他们把相关的邪恶本性带给他自己。我们现在勾勒出了他的生活图景了吗？”\n“勾勒出了。”他说。\n苏：“假如在一个国家里这样的人只是少数，大部分人都是正常的，那么，这少部分人就会成为那些想要他们去参加战争的外国僭主的护卫或雇佣兵。如果没有发生战争，那么他们就会待在本国，搞一些小恶作剧。”\n阿：“什么样的恶作剧呢？”\n苏：“比如说，他们会当小偷、扒手、强盗，抢劫神庙，拐卖人口。如果他们善于言辞，那么就会成为告密者、伪证人，收受贿赂。”\n阿：“虽然犯这类罪的人也不多，但是也算得上一类罪恶。”\n“是的，”我说，“但是小恶和大恶是相对而言的。这种种事情，就其给国家造成的苦害来说，与一个僭主暴君造成的危害相比还是相差十万八千里的。然而当这样的害群之马和他们的众多跟随者在意识到他们的力量以后，就会凭着人民群众的愚昧，从他们中间挑选一个灵魂上最具有暴君潜质的人出来，这样他们便创造了他们的僭主。”\n“是的，”他说，“这样的人是最适合当僭主的。”\n苏：“如果人民拒绝他，那倒还好。但是如果是这样，一旦掌权，他就会像打自己的父母那样打击群众，像克里特人说的那样，让他的亲爱的父国或母国屈从于国家新生的统治者和管理者之下。这就是他的激情和欲望的目的。”\n阿：“就是那样的。”\n苏：“当这样的人还是独身，还没有得到权力的时候，他们的性格特点就是这样的。他们集合起他们的阿谀奉承者或者有用的工具。或者，如果他们想要得到别人的什么东西，他们会低三下四地在他们面前说话，表达他们的友好之情。但是一旦得手，他们便翻脸不认人了。”\n阿：“是的，很对。”\n苏：“他们从来都是别人的统治者或奴仆，但是永远都不是别人的朋友。僭主永远都尝不到真正的自由或友谊的滋味。”\n阿：“当然尝不到。”\n苏：“那么我们可以把这样的人叫作不可靠的人吗？”\n阿：“完全可以。”\n苏：“如果我们对于正义的定义是正确的话，那么他们就是面目丑陋，极不正义的喽？”\n“是的，”他说，“我们定义得很对。”\n“那么让我们用一句话来概括这种最坏的人的特点，”我说，“他们是醒着能干出睡梦中的事的那种人。”\n阿：“再正确不过了。”\n苏：“这正是一个得权的僭主天性使然要做的事，他活得越久，就越像一个僭主。”\n“那是当然的。”格劳孔说道，现在轮到他发话了。\n苏：“现在不是正能看出，最邪恶的人同样也是最不幸的人吗？那些专政时间越长越严厉的人，也是不幸持续时间最长的人，尽管大部分人的看法不是如此？”\n“是的，”他说，“必然是那样的。”\n苏：“专制君主的人不是像僭主政治的国家吗？民主的人不也就像民主政治的国家吗？如此等等。”\n格：“当然。”\n苏：“在美德和幸福方面，国家与国家的不同也就类似于人与人之间的不同不是吗？”\n格：“就是那样的。”\n苏：“那么和我们最初的由一个国王统治的国家比起来，由僭主统治的国家在美德方面有什么不一样呢？”\n“它们是两个相反的极端，”他说，“因为一个是最好的，另一个是最糟糕的。”\n“这样便不会有错了，”我说，“哪个是哪样的，简直是一目了然，因此我现在直接问你有没有得出它们谁更幸福谁更不幸的相似的结论。在这里我们一定不要让自己被僭主这个幻影搞疯，他只是一个利益集团，身边有少量的近卫队。让我们深入城邦的各个角落仔细观察看看，这样我们就能给出我们的意见了。”\n“这是一个很美好的邀请，”他答道，“大家一定都像我一样看到了，僭主政治是政府所采用的最不幸的形式，而由国王统治是最幸福的。”\n苏：“在评估一个人的时候，我可不可以作出一个公平的请求，那就是我应该进入一个人的内心，通过分析他的本质来评估他？人们不能像一个小孩子那样光是看他的外表，被僭主在旁观者面前假装出来的那种华而不实的表象所迷惑，而是要清清楚楚地把他看明白。我们要听从这样的有能力判断的人的审讯，他曾和僭主朝夕相处，知道他的日常生活和亲戚关系，看到他剥下了悲剧的伪装之后的样子，也看到他在公众面前的危险时刻——这样他才能告诉我们和其他人比较起来他到底是幸福还是不幸不是吗？”\n“这又是一个很不错的建议。”他说。\n苏：“我可不可以说我们自己就有能力和经验来进行判断，因为我们之前就遇到过僭主这样的人呢？那样的话我们当中就有人能够回答我们的问题了。”\n格：“一定是的。”\n苏：“请让我提醒你不要忘了个人和国家之间的平行对比，要把这一点牢牢记在心里，来回审视这二者。你可以告诉我们他们各自的特点吗？”\n“你说的是什么意思呢？”他问道。\n“首先从国家开始，”我答道，“你认为一座由僭主管理的城邦是自由的还是受奴役的呢？”\n“没有哪个城邦比这个城邦受到的奴役更多了。”他说。\n苏：“但是你看看，这样的国家里还是会有自由人和管理者啊？”\n“是的，”他说，“我看到了，是少数人。但是大体上，人民，包括其中最优秀的那些人都被悲惨地降了级，被奴役着。”\n“那么，如果一个人就像国家一样，”我说，“他们不就适用于同样的原则了吗？人的灵魂充斥着吝啬和粗俗，而最好的那些元素则被奴役着。虽然统治的部分是少数，但也是最坏最疯狂的部分。”\n格：“必然是那样。”\n苏：“你认为这样的灵魂是自由人的灵魂还是奴隶的灵魂呢？”\n格：“我认为他的灵魂是奴隶的灵魂。”\n苏：“那么这样的被僭主奴役的国家就完全不能随心所欲地做自己愿意做的事情喽？”\n格：“完全不能。”\n苏：“在僭主（我这里是把灵魂当作一个国家来看）统治下的灵魂也最不能做她想要做的事情了，就好像有一只牛虻在刺激她，她一身都是麻烦，并且充满了悔恨？”\n格：“当然了。”\n苏：“僭主统治的城邦是贫还是富呢？”\n格：“贫穷无比。”\n苏：“那么僭主式的灵魂也一定总是贫瘠并且贪得无厌的喽？”\n格：“没错。”\n苏：“这样的国家和人一定是时时充满恐惧的喽？”\n格：“是的，没错。”\n苏：“你能不能在别的哪个国家里发现比这个国家更多的哀悼、悲伤、呻吟还有痛苦呢？”\n格：“当然不能。”\n苏：“你能不能在别的哪个人身上发现比处于愤怒、激情和欲望中的僭主式的人物更多的痛苦呢？”\n格：“那是不可能的。”\n苏：“回想这种种迹象和类似的罪恶，你坚持认为僭主式国家是所有国家中最不幸的吗？”\n“我的想法是对的吧。”他说。\n“当然了。”我说，“如果你看到僭主式的人身上也有同样的罪恶，你如何看待他呢？”\n格：“我会认为他是目前为止最为不幸的人。”\n“打住，”我说，“我认为你开始搞错问题了。”\n格：“这是什么意思？”\n苏：“我认为他还没有达到最为极端的不幸。”\n格：“那么谁更加不幸呢？”\n苏：“我即将提到的这种人。”\n格：“是谁？”\n苏：“具有僭主本质的人，他过的不是普通公民的生活，他被更深沉的不幸所诅咒，当上了公众的僭主。”\n格：“总结以上你所说的，我认为你是对的。”\n“是的，”我答道，“但是在这样的高水平的辩论中，你应该让观点更加精确，而不能仅仅作出猜测。因为在所有的问题当中，有关善和恶的问题是最大的问题。”\n“非常正确。”他说。\n苏：“让我来为你说明一下，我认为这会让整个话题稍微水落石出一点。”\n格：“你如何说明呢？”\n苏：“拿城邦里拥有众多奴隶的富人来说明。从他们身上你也许能够看到僭主的影子，因为他们都拥有很多奴隶。唯一的不同点在于僭主的奴隶还要多。”\n格：“是的，那就是不同之处。”\n苏：“你知道他们过得很安心，一点都不忧虑他们的奴仆的事情是吧？”\n格：“他们又能害怕什么呢？”\n苏：“没有什么好害怕的。但是你观察出了其中的原因吗？”\n格：“我知道的。原因就在于，整个城邦的结盟就是因为它会保护每一个个体。”\n“非常正确。”我说，“但是假设有这么一个奴隶主，他有五十个奴隶。他和他的家人、财产和奴隶们一起，被神明带到了荒郊野地，在这里没有哪个自由人可以救他的命。他难道不会因为担心这些奴隶会处死他和他的一家老小而感到巨大的恐惧吗？”\n“是的，”他说，“他会感受到最大的恐惧。”\n苏：“这个时候就轮到他来讨好和他不同类的奴隶了，他只能违心地向他们作出许多类似于给予他们自由的承诺，他必须用甜言蜜语来应付他自己的奴仆。”\n“是的，”他说，“这是他拯救自己的唯一的方法。”\n苏：“假设还是刚刚那个把他带到荒郊的神明，在他周围布下了一圈不允许别人奴役他人的人，他们如果抓到了违反者，就会将他处死，那时会怎样呢？”\n格：“如果他的四周到处都围绕着监视他的敌人，他的处境就更糟了。”\n苏：“这难道不是一种困住僭主的监狱吗——那种我们所描述过的天性具有僭主气质的人，在这里充满了恐惧和欲望？他的灵魂挑剔而又贪婪，比城邦中的其他人都要孤独，他永远不能去旅行，也看不到其他自由人想要看的东西，而是像妇女一样身居闺中，只能嫉妒那些能够去国外旅行欣赏有趣的景物的人。”\n“非常正确。”他说。\n苏：“在所有这些邪恶当中，那些不能管理好自己的人——我的意思就是指僭主，也就是你刚刚所说的所有人中最不幸的人——如果没有过好自己的私人生活，而命运又强迫他成为大众的僭主，他的生活会更加不幸吗？他在不能管理好自己的情况下就要去管理别人：他就像那些身体不健全的人一样被迫放弃休养，要和其他人一起打仗斗争。”\n“是的，”他说，“他们看上去几乎一样。”\n苏：“这种情况不是极端不幸吗？真正的僭主的生活难道不是比你所认为的不幸的人的生活还要不幸吗？”\n格：“当然了。”\n苏：“不管人们怎么想，真正的僭主是真正的奴隶，他们必须展示最大的谄媚，呈现出最大的奴性的丑态，是最恶劣的人种。他的欲望往往大到难以满足，他的欲望也比别人的欲望要多得多。如果你懂得如何窥伺他的整个灵魂，那么你就能看到他的真实的贫穷。他终其一生都活在恐惧、幻想和焦虑中，甚至就像他所代表的那个国家一样。他所代表的国家也是那样的吧？”\n“非常正确。”他说。\n苏：“此外，正如我们之前所说，他有了权力以后变得更加糟糕了。他变得嫉妒、无信仰，越发得不正义，不友好，不虔诚。他热衷于实施各种罪行，结果就是他变得极度的不幸，也使得别人和他一样的不幸。”\n格：“没有人会怀疑你的话的。”\n“现在该轮到像裁判那样宣布最后的结果的时候了，”我说，“说说你是否决定了在你心目中最为幸福的那种人，以及第二幸福等等排名的人。他们一共有五种，分别是王者型、荣誉至上型、寡头型、民主型、僭主型人物。”\n“要给出答案是很简单的，”他答道，“假设他们是即将登上舞台的合唱队，我必须要根据美德和恶行、幸福和不幸的标准排列他们上场的顺序。”\n苏：“我们是让传令官还是让阿里斯顿的儿子（最好是他）来宣布呢？宣布最善最正义的人同时也是最幸福的人，也是那位能够控制自己并且最有王者气质的人；最恶最不正义的人同样也是最不幸的人，也就是那个本性就是僭主，同时也是国家最大的僭主的人。”\n“还是你自己来宣布吧。”他说。\n苏：“我要不要加上一句，‘不管有没有被神和人看到’？”\n格：“加上那些话吧。”\n“那么这就是我们第一手的证明，”我说，“还有一个，同样具有一定的分量。”\n格：“是什么？”\n苏：“第二个证明来自于灵魂的本性：你知道个人的灵魂和国家都被我们按照一定的原则分成了三个部分，我想，这个分类可以作为新的说明。”\n格：“是什么本性？”\n苏：“在我看来这三个部分正对应着三种快乐，同样还对应着三种欲望和统治的权力。”\n“这是什么意思呢？”他说。\n苏：“正如我们所说，其中一个部分是用来学习的，另一个部分是用来生气的，第三个部分，由于拥有多种形式，因此没有一个特定的名字，就要以其中最普遍常见的欲望来表示，从非凡的力量到热烈的吃喝的欲望，再到性欲，在这里面选择一个主要的元素，我们可以称之为爱财，因为所有这些欲望都必须有金钱的支持。”\n“那倒是真的。”他说。\n苏：“如果我们要说第三个部分的爱和欲望是与利益相关的，那么我们就可以退回到一个单一的观念上，也就是把人们容易理解的灵魂的真实部分描述为对利益和金钱的热爱。”\n格：“我同意你的说法。”\n苏：“再来，激情这个元素完全是设置来进行控制、统领和获取名誉的吗？”\n格：“没错。”\n苏：“我们把它叫作争强好胜或者是雄心勃勃的激情吧——这样称呼合适吗？”\n格：“特别合适。”\n苏：“另一方面，每一个人都能看到知识是完全指向真理的，与其他获利或获名的元素的关系不大。”\n格：“关系差远了。”\n苏：“那么我们就可以把‘智慧的热爱者’‘知识的热爱者’这样的头衔加到灵魂的这个部分上喽？”\n格：“当然了。”\n苏：“有些人的灵魂里盛行着一个原则，另一些人的灵魂里盛行别的原则，这样的情况是会发生的吧？”\n格：“是的。”\n苏：“那我们一开始就要假设有三类人——热爱智慧的人、热爱荣誉的人、热爱利益的人？”\n格：“就是那样。”\n苏：“同时他们也对应着三种快乐是吧？”\n格：“非常正确。”\n苏：“如果你观察一下这三类人，挨着问他们谁的生活最为快乐，他们都会高度赞扬自己的生活，贬低他人的生活。挣钱的人会把对荣誉的虚荣心或者学习的上进心进行对比，他会认为这二者不能带来金钱的实际利益不是吗？”\n“没错。”他说。\n苏：“至于热爱荣誉的人——他的想法又是如何呢？他难道不会认为富人的快乐粗俗不堪，而学习的快乐如果不能带来荣誉，对他来说也只是过眼云烟和无聊之事吗？”\n格：“非常正确。”\n“而我们要不要认为，”我说，“哲学家将其他快乐和获知真理的快乐相比较的时候，他会觉得对真理的执着的追求无论何时都离天堂的快乐不太遥远吗？他难道不是按照必然性的标准来选择快乐的吗，如果是非必要的快乐，他宁肯不要不是吗？”\n“这一点毫无疑问。”他答道。\n苏：“那么，由于每一类人的快乐和他们的生活存在争议，问题也不在于谁的生活更为可敬，或者是好是坏，而在于谁的生活更快乐或者说没有痛苦——我们又该如何知道谁的话是真的呢？”\n“我自己分辨不了。”他说。\n苏：“那么，评判标准是什么呢？有什么标准能比经验、智慧和理性更好吗？”\n“没有比它们更好的标准了。”他说。\n“那么，请考虑一下。”我说，“在这三类人中，谁拥有最多我们举出来的那些娱乐的经验？利益的热爱者在学习本质的真实的本性的时候，是不是比哲学家所拥有的获益的快乐更多？”\n“哲学家会享受到极大的快乐，”他答道，“因为他从小就有必要尝试其他的快乐。但是利益的热爱者在所有的经验中都没有必要去尝试——还是说，我应该说即使他想要那么做，他也尝试不了学习和获知真理的甜蜜。”\n苏：“那么智慧的热爱者岂不是因为有双倍的经验而比利益的热爱者拥有更大的好处吗？”\n格：“是的，非常大的利益。”\n苏：“并且，热爱荣誉的人的快乐的体验是不是比智慧者更多？”\n“不是的，”他说，“这三类人的比例是大致相同的，因为他们都实现了他们的目标。因为富人、勇敢的人还有智慧的人都同样拥有爱戴他们的人，他们在接受荣誉的时候就能享受到获得荣誉的快乐。但是，获得真理存在的知识的快乐只能在哲学家身上找到。”\n苏：“那么，他的经验就会让他比其他人更会判断喽？”\n格：“更会判断。”\n苏：“他也是唯一一个既有智慧又有快乐经验的人喽？”\n格：“当然了。”\n苏：“另外，作为判断的工具的那种能力也不会为贪婪或有雄心的人所有，而只能为哲学家所有？”\n格：“什么能力？”\n苏：“理性。有了理性，就能像我们说的那样得出结论了。”\n格：“是的。”\n苏：“那么理性就是他的特殊工具喽？”\n格：“当然。”\n苏：“如果用财富和利益作为评判标准，那么对于热爱利益者的褒贬显然就成为了最可靠的评判喽？”\n格：“显然是的。”\n苏：“或者，如果用荣誉或者胜利或者勇气作为评判标准，那么对于具有雄心和好胜的人的评判就是最真实的喽？”\n格：“很明显。”\n苏：“那么，如果用经验、智慧和理性作为判断……”\n“唯一可能推出的结论就是，”他答道，“智慧和理性的热爱者所体会的快乐就是最真实的。”\n苏：“现在我们已经得出了结论，灵魂的理性部分的快乐是三个部分当中最快乐的，也是引导最快乐的生活的统治原则。”\n“毫无疑问，”他说，“最具有权威性的是智慧之人说自己快乐的话。”\n苏：“那么根据判断，哪种生活和它的快乐排到第二呢？”\n格：“显然是士兵和热爱荣誉的人的生活。比起挣钱的人来，他们的生活更接近第一种。”\n苏：“最后才是热爱利益的人喽？”\n“非常正确。”他说。\n苏：“正义的人在这场战争中已经连续两次打倒不正义的人了。接下来是第三次磨炼，这次是献给奥林匹亚（Olympian）的宙斯这位拯救者的。一位圣人在我的耳边向我倾诉，他说没有什么快乐比智慧更加真实纯净了。其他的一切快乐都只是影子而已。这次就会证明到底是不是最大最决定性的失败不是吗？”\n格：“是的，是最重要的一次。但是你能先解释一下你的意思吗？”\n苏：“我来提问你来回答。”\n格：“说吧。”\n苏：“快乐和痛苦是相反的吗？”\n格：“没错。”\n苏：“有一种介于快乐和痛苦之间的状态吗？”\n格：“有。”\n苏：“这种状态位于中间，是一种灵魂的平静，既不快乐也不痛苦，你是这个意思吗？”\n格：“是的。”\n苏：“你知道人们生病的时候会说些什么吗？”\n格：“他们说些什么？”\n苏：“他们会说没有什么比健康更快乐的了。但是他们在生病以前就绝对不会想到这一点。”\n“是的，我知道。”他说。\n苏：“如果人们遭受了刻骨的疼痛，你也一定听到他们说过想要去除疼痛的话吧？”\n格：“我听到过。”\n苏：“还有许多其他这样的例子，人们把疼痛的暂时停止或去除当作最大的快乐，而不是把那些正面的娱乐当作最大的快乐？”\n“是的，”他说，“这个时候他们就满意了，保持平静就很快乐了。”\n苏：“再来，如果在没有正面的快乐的时候，这类平静和痛苦的终止也是痛苦的喽？”\n“确定无疑。”他说。\n苏：“那么这种处于平静的中间状态既可以是快乐的，也可以是痛苦的？”\n格：“看上去就是那样的。”\n苏：“两者都不是的东西能够变成两者皆是吗？”\n格：“我敢说不是的。”\n苏：“快乐和痛苦都是心灵的运动，不是吗？”\n格：“是的。”\n苏：“但是我们刚刚证明了这个二者皆不是的东西是一种平静，不是一种运动，而是痛苦和快乐的平均值不是吗？”\n格：“是的。”\n苏：“那么，如果我们说没有痛苦就是快乐，或者说没有快乐就是痛苦，这种说法可能正确吗？”\n格：“不可能。”\n苏：“这只是表象，而不是事实。也就是说，和痛苦的东西比较起来平静是一种快乐，和快乐的东西比较起来它又是一种痛苦。而如果用真正的快乐去测试这些表象，它们也只能是一种欺骗喽？”\n格：“可以这么推论。”\n苏：“你之前也许会认为，快乐就是痛苦的终止，痛苦就是快乐的终止，但是如果你看到了那种不带任何前置痛苦的快乐，就不会再这样认为了。”\n“它们到底是什么，”他说，“我又到哪里去寻找呢？”\n苏：“这种快乐是很多的：比如说嗅觉的快乐就是非常棒的，没有任何前置的痛苦。它们一瞬间而来，离开以后也不会留下任何痛苦。”\n“那倒是真的。”他说。\n苏：“那么我们就再也不要相信什么纯粹的快乐是痛苦的终止，纯粹的痛苦是快乐的终止这样的话了。”\n格：“不相信了。”\n苏：“不过，更多数量并且更强烈的那种从灵魂贯穿身体的快乐通常都是这种快乐，这种来自于痛苦的解脱的快乐。”\n格：“没错啊。”\n苏：“对于即将发生的快乐和痛苦的预感不也具有类似的特性吗？”\n格：“是的。”\n苏：“要我说明一下吗？”\n格：“洗耳恭听。”\n苏：“你同意人在本质上可以分为上、中、下三等吧？”\n格：“我同意。”\n苏：“如果一个人从最低等级上升到了中等，他难道不会认为他往上爬了吗？当他站在中层看他所来的地方，又没有看到真正的上层世界的时候，他难道不会以为自己已经处于最高级了吗？”\n“一定的，”他说，“他难道还会做他想吗？”\n苏：“如果他被带回原地，他难道不会真真实实地认为自己降级了吗？”\n格：“毫无疑问。”\n苏：“这些想法难道不都是因为他对于真正的上中下等级的无知吗？”\n格：“是的。”\n苏：“你会不会认为那些没有经历过真理的人，会像错误对待其他许多事情那样，对于快乐、痛苦和二者的中间状态有错误的看法。因此，他们一旦遭遇了一点痛苦，他们就会认为他们体验的痛苦是真实的，同样，一旦靠近了那个中立的或者说中间的状态，他们就会坚定地认为他们已经满足了快乐的欲望了。他们并不知道真正的快乐，错误地把痛苦和无痛进行了比较，就好像不拿白色却拿灰色和黑色比较一样。你认为我说的这种情况奇怪吗？”\n格：“不，一点也不奇怪。如果不是这样我才感到奇怪呢。”\n苏：“看看下面的问题吧——饥饿、口渴以及类似的事情，是一种身体状态的空虚吗？”\n格：“是的。”\n苏：“无知和愚蠢是灵魂的空虚吗？”\n格：“没错。”\n苏：“而食物和智慧可以分别满足这两种空虚吗？”\n格：“当然。”\n苏：“满足没那么充实的东西和满足较为充实的东西比较起来，哪一种存在更加真实？”\n格：“显然是满足较为充实的东西这种。”\n苏：“下面两类东西在你看来哪一种是更加纯粹的存在呢——是食物、饮料、调味品这类维持生计的东西，还是包含了真实意见、知识、思想的东西以及各类美德呢？让我们换个说法来阐明这个问题吧：下面哪一种是更加纯粹的存在——一种是永恒不变、长存不朽、充满真实的本身以及拥有这些性质的事物，一种是变化、消亡本身以及拥有这些性质的事物？”\n“永恒不变的才是更加纯粹的。”他答道。\n苏：“那么永恒不变的本质与它的可知程度是相当的吗？”\n格：“是的，与可知程度相当。”\n苏：“真理的本质也与它的可知程度相当吗？”\n格：“是的。”\n苏：“那么，反过来说，也就是不太具备真理的事物也就本质不实喽？”\n格：“必然是那样的。”\n苏：“那么，这样说来，服务于身体的器官也就比服务于灵魂的东西拥有较少的真理和本质喽？”\n格：“要差得远了。”\n苏：“身体本身是不是就不像灵魂那样拥有真理和实在？”\n格：“是的。”\n苏：“填充了更具真实性的东西的器物也就拥有了更真实的存在，并且比填充了较少真实性的器物更加真实吗？”\n格：“当然。”\n苏：“如果填充的实在顺应自然，令人快乐的话，那么填充的更加真实的存在就会更加真实，我们也能感受到更充实的快乐。反之亦然？”\n格：“毫无疑问。”\n苏：“那些不懂得智慧和美德的人，总是忙于暴饮暴食和满足性欲，在中下两级之间往返。他们以为自己如鱼得水，但是他们从来没有到达过真正的高层世界。他们从来没有抬头仰望过，也找不到向上走的道路，从来没有被真实存在填满心灵，也尝不到纯粹的永恒的快乐。他们就像牲畜一样总是头往下看，俯视着它们进食的地面，吃饱喝足，繁殖生长，在这些欢乐之余，便用角和钉铁的蹄互顶对方。他们由于自己的贪得无厌的欲望而解决掉别人，因为他们用以填充自己的东西并不充实，而是没有实质和毫无节制的东西。”\n“真的，苏格拉底，”格劳孔说，“你描述这些人的生活的话简直像神的预言一样。”\n苏：“他们的快乐和痛苦混杂在一起——又如何有其他的生活？因为那些只不过是真实的影子和幻象，相比之下显得多姿多彩，放大了光亮和阴影，于是在愚蠢的人心中种下了疯狂的欲望。他们就像斯特西科罗斯（stesichorus）说的那样像希腊人在特洛伊战争中由于对真理的无知而为了海伦的影子而战。”\n格：“这类事情一定会发生的。”\n苏：“同样的事情难道不会发生在灵魂的激情或者热烈部分之上吗？富有激情的人热情对待他的行为，不管他是容易嫉妒还是雄心勃勃，是暴力分子还是争强好胜，是容易发怒的还是容易不满的，如果他想方设法去追求荣誉、胜利以及愤怒的平息，无视理性和道理，难道不是一样的吗？”\n“是的，”他说，“同样的事情也会发生在激情这个元素身上。”\n苏：“那么我们就可以断言，如果金钱和荣誉的热爱者在理性和知识的指导下追寻他们的快乐，探寻并获取智慧向他们展示的快乐，他们一样会发现他们能够接触的最高等级的最纯粹的快乐，因为他们是追随着真理的。如果说对于每个人来说最好的快乐就是最适合他的快乐，那么他们就会得到这种最适合的快乐。”\n格：“是的，当然，最好的就是最适合的。”\n苏：“当整个灵魂都跟随着哲学性的原则，没有分裂，每个部分都正义的时候，那么它们每个部分就都能做好自己的分内事，享受对它们来说的最好最纯净的快乐不是吗？”\n格：“显然是那样。”\n苏：“但是如果任其中两个占据大部分，它就会得不到自己固有的快乐，并且会迫使剩下的一个部分去追求不属于它们的影子？”\n格：“没错。”\n苏：“它们离哲学和理性的距离越远，快乐也就变得更加陌生和迷惑人喽？”\n格：“是的。”\n苏：“离理性最远的不就是离法律和秩序最远的吗？”\n格：“显然是的。”\n苏：“依我们所见，最贪婪最僭主式的欲望就是离它最远的？”\n格：“是的。”\n苏：“王者的有秩序的欲望是离得最近的？”\n格：“是的。”\n苏：“那么僭主就住得离真实或者说最适合他的快乐最远，而国王是最近的？”\n格：“当然。”\n苏：“但如果是这样的话，僭主就过得最不愉快，而国王是过得最愉快的？”\n格：“显而易见。”\n苏：“你知道如何测量他们之间快乐的差距吗？”\n格：“你能告诉我吗？”\n苏：“有三种快乐，一种是真实的，另外两种是虚假的。而僭主的快乐已经超越了这两种虚假的快乐，他远离了法律的合理性，他的周围全是卫星一样包围着他的奴役的快乐，对他的劣势的测量只能用数字来表示。”\n格：“如何表示？”\n“我假设僭主离寡头派差三级，”我说，“中间则是民主派喽？”\n格：“是的。”\n苏：“如果之前有关真理的话是对的，那么他所享有的快乐离真理的快乐的距离就是寡头派的快乐离真理的快乐的距离的三倍远？”\n格：“就是那样。”\n苏：“而寡头派相对于国王来说也是三倍远，因为我们还算上了在他之上的王者和贵族？”\n格：“是的，他排在第三位。”\n苏：“那么，僭主离真实的快乐的距离就是三乘以三那么远？”\n格：“非常清楚。”\n苏：“这样，僭主所享受的阴影般的快乐就用这样一个度量长度的平面的数字来表示了。”\n格：“当然了。”\n苏：“如果你用力把这个平面拉成一个立方体，你就会毫不费力地看到僭主的快乐离国王的快乐有多遥远。”\n格：“是的，算术家是很容易计算出来的。”\n苏：“如果有谁来测量一下位于两端的僭主和国王的快乐，当他算完三次方以后，就会发现国王比僭主要快乐729倍，而僭主也要比国王痛苦729倍。”\n格：“多么神奇的计算啊！关于快乐和痛苦，正义和不正义的距离是有多远啊！”\n“这只是一个真实的计算，”我说，“如果人类的生活和年月日有关，那么数字就可以计算人类的生活。”1\n“是的，”他说，“人类的生活当然和这些有关。”\n苏：“那么，如果善良正义的人的快乐超出邪恶不正义的人那么多，这种生活的优势在美和美德上面不是更明显吗？”\n格：“要明显得多啊。”\n“好吧，”我说，“现在我们已经来到了讨论的这个阶段，我们可以回到最开始说的内容上去。是不是有人说那些名誉上被认为是正义的却极端不正义的人可以从不正义身上得到好处？”\n格：“是的，是说过那样的话。”\n苏：“那么，既然已经确定了正义和不正义的力量和特性，就让我们跟提出这一说法的人来对对话吧。”\n格：“我们应该对他说些什么呢？”\n苏：“我们可以塑造出灵魂的形象，让他说的话好似历历在目。”\n格：“是哪种形象呢？”\n苏：“这是一个完美的理想形象，就像古代神话中的那些复合型的创造一样，比如喀迈拉（Chimera）或者斯库拉（Scylla）或者刻耳柏洛斯（Cerberus），还有其他许多这样的把两种或更多的特点融合到一个生物身上的东西。”\n格：“据说是有这样的结合体。”\n苏：“现在请你设想一只由各种形象组成的多头怪兽，它的头部结合了各种野兽的样子，温驯的、凶猛的，它能随心所欲地变化头部。”\n格：“塑造你所说的形象的塑造家一定拥有不可思议的力量。不过，既然语言是一种比蜡或者其他物质更加柔韧更容易塑造的东西，就假设你的模型成立吧。”\n苏：“现在假设再塑造一头狮子的形象，第三个是一个人的形象，第二个形象比第一个小一些，第三个又比第二个还小些。”\n“这个任务就简单些了，”他说，“我已经按照你说的塑造好了。”\n苏：“现在把这三者结合起来，成为一个形象。”\n格：“完成了。”\n苏：“接着让它们的外表融为一体，做成人形，这样那些看不到内在的人就只能看到一个外壳，他们就会相信这个野兽和这个人是同一个生物了。”\n“我已经做好了。”他说。\n苏：“现在，对那个坚持认为人类做不正义的事对自己有利而做正义的事不利的人，我们就要回答他，如果他说的话是对的，也就等于认为让那个多样的怪物享受盛宴，加强狮子的力量以及具有狮子本性的部分是有利的，他认为要让其中的人挨饿虚弱，不应该因为对其另外二者的怜悯而被牵制，他应该任由它们争斗、撕咬、吞食。”\n“当然，”他说，“同意不正义的人就会那样说。”\n苏：“而支持正义的人则会回答说，他应该想方设法地对存在于他内心中的那份人性进行引导，让它来控制自己整个人。他应该像一个尽职的农夫浇灌他的作物避免野草生长那样看守好这个长着人头的怪物。需要注意的最基本的地方就是要让各个部分都能成为他内心的整体。”\n“是的，”他说，“正义的拥护者就会那样说。”\n苏：“因此从各个角度来看，不管是从快乐、荣誉还是利益上来看，支持正义的人都是对的，他们说的是真理，而不支持正义的人是错误的，并且很无知是吗？”\n格：“是的，从各个角度看都是如此。”\n苏：“现在让我们温和地规劝一下那些不正义的人吧，他们并不是故意犯错的。我们应该对他说：‘亲爱的先生，你如何看待被人认为是高尚的和丑陋的东西？高尚的难道不是兽性向人性屈服的部分，或者说是人性中的神性部分？而丑陋的难道不是人性向兽性屈服的部分？’他很难否定这一点吧——我们现在要问吗？”\n格：“如果他听进去了我的意见就会同意的。”\n苏：“但是，就算他同意了这个说法，我们还要问他另一个问题：‘如果一个人依靠将自己内心最神圣的部分交给最坏的部分奴役而获得了金银，能说他获益了吗？谁能想象一个人为了钱财卖掉自己的儿女，尤其是卖到最凶猛最邪恶的人手上，而得到钱财的人，不管分得的钱财的数目有多大，能说他得到的全是利益吗？难道会有人说他并不是一个不幸的卑劣的人，不是冷酷无情地向最无神性最可憎的存在出卖了他最神圣的存在？厄里费勒（Eriphyle）为了一条项链付出了她丈夫的一条性命，他因为这份贿赂而迎来了更惨的灭亡。’”\n“是的，”格劳孔说，“还要悲惨啊——我来替他回答吧。”\n苏：“放纵经常受到谴责难道不是因为人们给了内心的那个巨大的多样怪兽太多自由吗？”\n格：“显然是的。”\n苏：“当他心中的狮子和巨蛇的元素过度成长获得力量的时候，人们不是就会因为骄傲自满和坏脾气受到责备吗？”\n格：“是的。”\n苏：“奢侈和软弱受到责备，是因为他们放松了这个生物，使之变成了一个懦夫吗？”\n格：“非常正确。”\n苏：“如果人们让管理激情的动物的部分屈服于这个不统大权的怪兽，他难道不是更加接近谄媚者和吝啬者了吗？其次，为了他总是感觉不够多的钱财，他从小就习惯在泥沼中受到践踏，本来应该成为一头雄狮，却变成了一只猴子？”\n“没错。”他说。\n苏：“为什么那些卑贱的职业和手工艺者受到羞辱？就是因为他们在更高的原则面前表现了天生的软弱，控制不了内心的各种生物，只能奉承它们，使奉承成为了他的一大课题。”\n格：“看来这个就是原因。”\n苏：“因此，我们把他放到最好的控制之下也就等于让他做最优秀的人物的奴隶，处于神圣的统治之下，而不是像色拉叙马霍斯认为的那样使他这个奴隶受到伤害，而是因为每个人都最好能够被居住在他心里的那份神圣的智慧所统治。如果做不到这一点，也要尽量做到让统治的力量来自于内部，而在这个统治之下，大家能够成为平等的朋友。”\n“没错。”他说。\n苏：“显然这也是法律的目的，而法律正是整个城邦的盟友。这也是我们在孩子们身上实施的权威，并且，直到我们在他们身上建立了与国家制度相类似的原则，使我们塑造的这个更高的元素在他们心里生根，成为像我们的护卫者一样的护卫者和统治者，我们才能放他们自由，才能让他们走自己的路。”\n“是的，”他说，“很明显这是法律的目的。”\n苏：“那么，如果一个人通过不正义或者不节制或者其他的卑鄙行为变成了一个更坏的人，哪怕他从他的邪恶当中获得了一定的金钱和权力，我们又能通过哪种观点才能证明这样的行为对他有益呢？”\n格：“根本无法证明。”\n苏：“如果他的不正义没有被揭发出来，他也逃过了惩罚，这对他有什么好处呢？他只能变得更坏，而被揭发被惩罚的人却能让天性中残忍的部分平静下来，变得人性化。这样，他内心的温和的元素就无拘无束了，整个灵魂也得到了完善，由于获得了正义、节制和智慧而变得高贵，比天生丽质、有力健康的外表更好，因为灵魂本来就比身体更值得尊敬。”\n“当然了。”他说。\n苏：“为了这个高贵的目标，有识之人会献上他的生命的全部精力。并且，他会首先尊崇那些能够加强这些灵魂上的品质的学问，而不顾其他的学问不是吗？”\n“显然是的。”他说。\n苏：“其次，他会调节他的身体的习惯和锻炼，尽量避免野蛮不理性的娱乐，甚至会把健康当作次要的事情。他的首要目标并不是要变得健美、强壮或者健康，除非这些锻炼能让他获得节制。他的首要目标永远都是想要通过调节身体来维持灵魂的和谐不是吗？”\n格：“如果他的内心有着真正的音乐，那么他当然就会这样做。”\n苏：“在获得财富的事情上，他同样会遵循有序和谐的原则。他不会让自己愚蠢到被满世界的赞美冲昏了头脑，空累财富给自己带来无穷的害处，是吗？”\n“他当然不会那样做。”他说。\n苏：“他会注视着内心的城市，不让里面产生有可能产生的由奢侈和欲望引起的不和。他根据这个原则调节他的财富，遵循他的方式，要么挣取，要么消费。”\n格：“非常正确。”\n苏：“同时，基于同样的原因，他会逐渐地接受并享受他心目中能让他成为一个更好的人的那些荣誉。而不管是私下里还是在公共场合，他都会拒绝那些打乱他的生活的东西？”\n格：“如果他有这样的念头，他是不会成为一个政治家的。”\n苏：“埃及的神啊，他会的！在属于他的城邦里他当然会，尽管他在自己出生的城邦也许不会，除非有神迹。”\n格：“我懂了。你的意思是他会成为我们所建立的那个只存在于理想中的城邦的统治者。我想这个世界上还不存在这样的城邦吧？”\n“我想，在天堂里就有一座这样的城邦的模型吧，”我答道，“希望它存在的人就能看见它，一旦看见了，就会一个接一个在那里定居下来。但是现在存在与否以及以后是否会出现都不是重点，因为他会模仿这个城邦的方式生活，和其他城邦没有关系。”\n“我想是的。”他说。"}, {"type": "text", "value": "[1]729相当于一年之中白昼和黑夜的总数。——译者注"}]}