{"title": "1891年德文第四版序言", "index": 215, "content": [{"type": "text", "value": "1891年德文第四版序言 [258]"}, {"type": "text", "value": "我曾经预料，这篇论文的内容对我们的德国工人来说困难是不多的，现在这个预料已被证实。至少从1883年3月第一版问世以来已经印行了三版，总数达1万册，而且这是在现今已寿终正寝的反社会党人法的统治下发生的事情。同时，这也是一个新的例证，说明警察的禁令在像现代无产阶级的运动这样的运动面前是多么软弱无力。"}, {"type": "text", "value": "从第一版印行以来，又出版了几种外文译本：帕斯夸勒·马尔提涅蒂翻译的意大利文本《空想社会主义和科学社会主义》1883年贝内文托版；俄文本《科学社会主义的发展》1884年日内瓦版；丹麦文本《社会主义从空想到科学的发展》，载于《社会主义丛书》第一卷，1885年哥本哈根版；西班牙文本《空想社会主义和科学社会主义》1886年马德里版；以及荷兰文本《社会主义从空想到科学的发展》1886年海牙版。"}, {"type": "text", "value": "本版作了一些小的修改；比较重要的补充只有两处：在第一章中关于圣西门的补充，同傅立叶和欧文相比，关于圣西门过去谈得有点过于简略；其次是在第三章接近末尾处关于在这期间已经变得很重要的新的生产形式“托拉斯”的补充 [259]。"}, {"type": "text", "value": "弗里德里希·恩格斯"}, {"type": "text", "value": "1891年5月12日于伦敦"}, {"type": "text", "value": "弗·恩格斯写于1891年5月12日"}, {"type": "text", "value": "载于1891年在柏林出版的恩格斯《社会主义从空想到科学的发展》一书"}, {"type": "text", "value": "原文是德文"}, {"type": "text", "value": "中文根据《马克思恩格斯全集》德文版第22卷翻译"}, {"type": "text", "value": "[258] 这篇序言是恩格斯为他的著作《社会主义从空想到科学的发展》德文第四版写的。该版于1891年在柏林由《前进报》社出版。第四版是恩格斯生前以德文印刷的最后一版。——497。"}, {"type": "text", "value": "[259] 恩格斯提到的对《社会主义从空想到科学的发展》最初文本的补充，另行刊载在《马克思恩格斯文集》第9卷《〈反杜林论〉准备材料》部分。——497。"}]}