{"byPath": {"东方/###合集&概述###/中国佛教史.epub": 127, "东方/###合集&概述###/中国哲学简史.epub": 121, "西方/###合集&概述###/刘擎西方现代思想讲义.epub": 142, "西方/###合集&概述###/大问题.epub": 223, "西方/###合集&概述###/给青年人的哲学十二讲.epub": 54, "西方/###合集&概述###/苏菲的世界（贾德名作系列三部曲）.epub": 433, "西方/###合集&概述###/西方哲学史（英汉对照）.epub": 1582, "西方/###合集&概述###/西方百年学术经典著作.epub": 4370, "西方/乔治·巴塔耶/内在体验.epub": 142, "西方/亚当·斯密/国富论.epub": 307, "西方/亚当·斯密/道德情操论.epub": 219, "西方/亚里士多德/工具论.epub": 221, "西方/亨利·戴维·梭罗/瓦尔登湖.epub": 190, "西方/伊壁鸠鲁/快乐主义.epub": 33, "西方/伊曼努尔·康德/康德文集.epub": 3066, "西方/伏尔泰/伏尔泰传.epub": 32, "西方/伏尔泰/天真汉.epub": 37, "西方/伏尔泰/查第格.epub": 41, "西方/伯特兰·罗素/幸福之路.epub": 276, "西方/伯纳德·斯蒂格勒/技术与时间.epub": 398, "西方/克洛德·列维-斯特劳斯/忧郁的热带.epub": 219, "西方/勒内·笛卡尔/方法论·情志论.epub": 59, "西方/勒内·笛卡尔/第一哲学沉思集.epub": 96, "西方/卡尔·古斯塔夫·荣格/心理学和炼金术.epub": 111, "西方/卡尔·古斯塔夫·荣格/红书.epub": 292, "西方/卡尔·波普尔/历史主义贫困论.epub": 91, "西方/卡尔·波普尔/开放社会及其敌人.epub": 251, "西方/卡尔·波普尔/猜想与反驳（二十世纪西方哲学经典）.epub": 262, "西方/卡尔·雅斯贝尔斯/时代的精神状况.epub": 90, "西方/卡尔·马克思/资本论.epub": 1279, "西方/卡尔·马克思/马克思恩格斯文集.epub": 4406, "西方/古斯塔夫·勒庞/乌合之众：大众心理研究.epub": 90, "西方/尤尔根·哈贝马斯/公共领域的新结构转型.epub": 40, "西方/弗朗茨·卡夫卡/变形记.epub": 231, "西方/弗朗茨·卡夫卡/城堡.epub": 147, "西方/弗里德里希·尼采/偶像的黄昏.epub": 71, "西方/弗里德里希·尼采/善恶的彼岸.epub": 170, "西方/弗里德里希·尼采/尼采哲学经典（套装共5册）.epub": 410, "西方/弗里德里希·尼采/尼采经典著作及研究丛书（四册全）.epub": 147, "西方/弗里德里希·尼采/查拉图斯特拉如是说.epub": 1197, "西方/弗里德里希·恩格斯/《反杜林论》导读.epub": 71, "西方/弗里德里希·恩格斯/家庭、私有制和国家的起源.epub": 83, "西方/弗里德里希·恩格斯/马克思恩格斯文集.epub": 4406, "西方/托马斯·莫尔/乌托邦.epub": 71, "西方/托马斯·霍布斯/利维坦.epub": 16, "西方/格奥尔格·威廉·弗里德里希·黑格尔/哲学科学全书纲要.epub": 558, "西方/格奥尔格·威廉·弗里德里希·黑格尔/法哲学原理.epub": 176, "西方/格奥尔格·威廉·弗里德里希·黑格尔/黑格尔作品集（套装共14册）.epub": 2802, "西方/约翰·斯图尔特·密尔/功利主义.epub": 41, "西方/约翰·斯图尔特·密尔/论自由.epub": 61, "西方/约翰·杜威/民主主义与教育.epub": 171, "西方/约翰·洛克/洛克.epub": 39, "西方/罗兰·巴特/符号帝国.epub": 33, "西方/莫里斯·梅洛-庞蒂/知觉现象学.epub": 275, "西方/西奥多·阿多诺/美学理论.epub": 320, "西方/西格蒙德·弗洛伊德/弗洛伊德文集.epub": 1860, "西方/西格蒙德·弗洛伊德/文明及其不满.epub": 81, "西方/西格蒙德·弗洛伊德/梦的解析.epub": 626, "西方/西格蒙德·弗洛伊德/自我与本我.epub": 98, "西方/西蒙娜·德·波伏娃/第二性（合卷本）.epub": 432, "西方/让-雅克·卢梭/忏悔录.epub": 33, "西方/让-雅克·卢梭/论人类不平等的起源和基础.epub": 66, "西方/费奥多尔·陀思妥耶夫斯基/卡拉马佐夫兄弟.epub": 460, "西方/费奥多尔·陀思妥耶夫斯基/陀思妥耶夫斯基集（全九册）.epub": 2379, "西方/赫伯特·斯宾塞/论正义.epub": 126, "西方/赫伯特·马尔库塞/单向度的人.epub": 105, "西方/阿图尔·叔本华/充足理由律的四重根.epub": 73, "西方/阿图尔·叔本华/叔本华哲学经典（套装共5册）.epub": 377, "西方/阿尔贝·加缪/加缪全集.epub": 1070, "西方/阿尔贝·加缪/加缪全集（小说卷）.epub": 327, "西方/阿尔贝·加缪/加缪全集（戏剧卷）.epub": 289, "西方/阿尔贝·加缪/加缪全集（散文卷Ⅰ）.epub": 208, "西方/阿尔贝·加缪/加缪全集（散文卷Ⅱ）.epub": 243, "西方/阿尔贝·加缪/反与正·婚礼集·夏.epub": 164, "西方/阿尔贝·加缪/在我身上有一个不可战胜的夏天.epub": 67, "西方/阿尔贝·加缪/西西弗神话.epub": 67, "西方/阿尔贝·加缪/鼠疫.epub": 100, "西方/雅克·德里达/德里达（牛津通识读本）.epub": 52, "西方/雅克·德里达/论文字学.epub": 213, "西方/马丁·海德格尔/存在与时间.epub": 223, "西方/马克斯·霍克海默/启蒙辩证法.epub": 165, "西方/马克斯·韦伯/新教伦理与资本主义精神.epub": 293, "西方/马可·奥勒留/沉思录.epub": 49, "西方/马基雅维利/君主论（拿破仑批注版）.epub": 119, "西方/马基雅维利/马基雅维利.epub": 540, "西方/马基雅维利/马基雅维利语录.epub": 34, "西方/鲁道夫·卡尔纳普/世界的逻辑构造.epub": 163}, "byTitle": {"中国佛教史||###合集&概述###": 127, "中国哲学简史||###合集&概述###": 121, "刘擎西方现代思想讲义||###合集&概述###": 142, "大问题||###合集&概述###": 223, "给青年人的哲学十二讲||###合集&概述###": 54, "苏菲的世界（贾德名作系列三部曲）||###合集&概述###": 433, "西方哲学史（英汉对照）||###合集&概述###": 1582, "西方百年学术经典著作||###合集&概述###": 4370, "内在体验||乔治·巴塔耶": 142, "国富论||亚当·斯密": 307, "道德情操论||亚当·斯密": 219, "工具论||亚里士多德": 221, "瓦尔登湖||亨利·戴维·梭罗": 190, "快乐主义||伊壁鸠鲁": 33, "康德文集||伊曼努尔·康德": 3066, "伏尔泰传||伏尔泰": 32, "天真汉||伏尔泰": 37, "查第格||伏尔泰": 41, "幸福之路||伯特兰·罗素": 276, "技术与时间||伯纳德·斯蒂格勒": 398, "忧郁的热带||克洛德·列维-斯特劳斯": 219, "方法论·情志论||勒内·笛卡尔": 59, "第一哲学沉思集||勒内·笛卡尔": 96, "心理学和炼金术||卡尔·古斯塔夫·荣格": 111, "红书||卡尔·古斯塔夫·荣格": 292, "历史主义贫困论||卡尔·波普尔": 91, "开放社会及其敌人||卡尔·波普尔": 251, "猜想与反驳（二十世纪西方哲学经典）||卡尔·波普尔": 262, "时代的精神状况||卡尔·雅斯贝尔斯": 90, "资本论||卡尔·马克思": 1279, "马克思恩格斯文集||卡尔·马克思": 4406, "乌合之众：大众心理研究||古斯塔夫·勒庞": 90, "公共领域的新结构转型||尤尔根·哈贝马斯": 40, "变形记||弗朗茨·卡夫卡": 231, "城堡||弗朗茨·卡夫卡": 147, "偶像的黄昏||弗里德里希·尼采": 71, "善恶的彼岸||弗里德里希·尼采": 170, "尼采哲学经典（套装共5册）||弗里德里希·尼采": 410, "尼采经典著作及研究丛书（四册全）||弗里德里希·尼采": 147, "查拉图斯特拉如是说||弗里德里希·尼采": 1197, "《反杜林论》导读||弗里德里希·恩格斯": 71, "家庭、私有制和国家的起源||弗里德里希·恩格斯": 83, "马克思恩格斯文集||弗里德里希·恩格斯": 4406, "乌托邦||托马斯·莫尔": 71, "利维坦||托马斯·霍布斯": 16, "哲学科学全书纲要||格奥尔格·威廉·弗里德里希·黑格尔": 558, "法哲学原理||格奥尔格·威廉·弗里德里希·黑格尔": 176, "黑格尔作品集（套装共14册）||格奥尔格·威廉·弗里德里希·黑格尔": 2802, "功利主义||约翰·斯图尔特·密尔": 41, "论自由||约翰·斯图尔特·密尔": 61, "民主主义与教育||约翰·杜威": 171, "洛克||约翰·洛克": 39, "符号帝国||罗兰·巴特": 33, "知觉现象学||莫里斯·梅洛-庞蒂": 275, "美学理论||西奥多·阿多诺": 320, "弗洛伊德文集||西格蒙德·弗洛伊德": 1860, "文明及其不满||西格蒙德·弗洛伊德": 81, "梦的解析||西格蒙德·弗洛伊德": 626, "自我与本我||西格蒙德·弗洛伊德": 98, "第二性（合卷本）||西蒙娜·德·波伏娃": 432, "忏悔录||让-雅克·卢梭": 33, "论人类不平等的起源和基础||让-雅克·卢梭": 66, "卡拉马佐夫兄弟||费奥多尔·陀思妥耶夫斯基": 460, "陀思妥耶夫斯基集（全九册）||费奥多尔·陀思妥耶夫斯基": 2379, "论正义||赫伯特·斯宾塞": 126, "单向度的人||赫伯特·马尔库塞": 105, "充足理由律的四重根||阿图尔·叔本华": 73, "叔本华哲学经典（套装共5册）||阿图尔·叔本华": 377, "加缪全集||阿尔贝·加缪": 1070, "加缪全集（小说卷）||阿尔贝·加缪": 327, "加缪全集（戏剧卷）||阿尔贝·加缪": 289, "加缪全集（散文卷Ⅰ）||阿尔贝·加缪": 208, "加缪全集（散文卷Ⅱ）||阿尔贝·加缪": 243, "反与正·婚礼集·夏||阿尔贝·加缪": 164, "在我身上有一个不可战胜的夏天||阿尔贝·加缪": 67, "西西弗神话||阿尔贝·加缪": 67, "鼠疫||阿尔贝·加缪": 100, "德里达（牛津通识读本）||雅克·德里达": 52, "论文字学||雅克·德里达": 213, "存在与时间||马丁·海德格尔": 223, "启蒙辩证法||马克斯·霍克海默": 165, "新教伦理与资本主义精神||马克斯·韦伯": 293, "沉思录||马可·奥勒留": 49, "君主论（拿破仑批注版）||马基雅维利": 119, "马基雅维利||马基雅维利": 540, "马基雅维利语录||马基雅维利": 34, "世界的逻辑构造||鲁道夫·卡尔纳普": 163}, "charPerPage": 1500, "total": 87}