{
  "era": "1925-1995",
  "country": "法国",
  "school": "后结构主义",
  "bio": "吉尔·德勒兹，1925年生于法国巴黎，1995年因病自杀辞世，作为后结构主义哲学的标志性人物，他以颠覆传统形而上学和创造异质概念著称，其思想深刻影响了当代哲学、艺术、文学和政治理论。德勒兹的哲学体系高度原创，拒绝系统化的教条，却以“差异”、“生成”和“欲望”为核心，构建了一套动态的、非中心化的世界观。他的工作常与精神分析学家费利克斯·加塔利合作，但即使独立创作，他也展现出对西方哲学传统的激进重读，从斯宾诺莎、尼采到柏格森，他从中提取出对抗同一性和再现逻辑的力量。\n\n德勒兹的核心哲学思想首先体现在他对“差异”的重新定义。传统哲学自柏拉图以来，往往将差异视为同一性的附属，即事物通过比较而呈现不同，但德勒兹在《差异与重复》中颠覆了这一等级制。他主张差异是自发的、原初的，而非从同一中派生。差异不是两个相似物之间的外在区别，而是内在的、创造性的力量，它驱动着世界的生成。德勒兹通过“重复”概念进一步阐释：重复不是相同事物的再现，而是差异的自我更新，每一次重复都携带着不可还原的变异。这种观点解构了本质主义，强调存在本身就是差异之流，没有固定的根基，只有不断分化的过程。这为后现代思想提供了本体论基础，批判了身份政治和形而上学二元论。\n\n其次，德勒兹提出了“生成”理论，这是其哲学的另一支柱。生成不是从一种状态过渡到另一种状态，而是摆脱固定形式、进入流动的、非人的过程。他区分了“生成-动物”、“生成-女人”和“生成-不可感知”等概念，强调生成不是模仿或隐喻，而是与异质元素建立连接，从而瓦解主体性。例如，在《卡夫卡：为弱势文学而作》中，德勒兹和加塔利分析了卡夫卡的作品，指出其人物通过生成-动物（如变成甲虫）来逃避父权和法律秩序。生成是一种逃逸线，它打破二元对立（如男/女、人/动物），指向一种分子层面的、微观的政治。这挑战了传统人文主义，将主体视为不断解域化的节点，而非理性中心。德勒兹的生成哲学还与他的“块茎”概念紧密相关：块茎是一种无中心、无等级的网络结构，如根茎或杂草，它不同于树状思维（强调根源和层级），允许任意连接和多元增殖。块茎式思维在《千高原》中被系统展开，成为德勒兹反系统哲学的典型方法论。\n\n第三，德勒兹对欲望的重新诠释是其思想中最具冲击力的部分。在《反俄狄浦斯》中，他与加塔利批判了弗洛伊德的精神分析，认为欲望不是匮乏（如拉康所主张），而是积极的、生产的机器。欲望是“欲望机器”，它不断连接、消耗和创造，驱动社会现实的生产。德勒兹和加塔利区分了“精神分裂”与“神经症”：神经症是欲望被社会编码和压抑的结果，而精神分裂则是欲望的解放性流动，它逃逸资本、家庭和国家的规训。他们提出“资本主义与精神分裂”的命题，认为资本主义既解构传统等级（如封建制），又通过私有财产和主体化重新编码欲望，造成普遍的“主体性危机”。欲望的政治学指向一种“游牧式”存在，即无根、流动、抵抗领土化的生活方式。这种理论影响了后马克思主义和激进左翼，尤其是对权力微观物理学的分析，与福柯的“生命权力”形成呼应。\n\n在哲学史地位上，德勒兹是后结构主义三巨头之一（与福柯、德里达并列），但他更侧重创造而非解构。他重读哲学史，将斯宾诺莎的“内在性”、尼采的“权力意志”和柏格森的“绵延”转化为自己的工具，从而构建了一条“反黑格尔”的哲学谱系。他对经验主义的改造（尤其是休谟）也极具特色，强调经验不是被动接受，而是实验和创造。德勒兹的影响跨越学科：在文学批评中，他的“弱势文学”概念启发了后殖民研究；在艺术理论中，他的“感觉逻辑”和“时间-影像”理论（与电影相关）成为电影研究经典；在政治学中，他的“游牧战争机器”被用于分析全球化和抵抗运动。然而，德勒兹也因晦涩和反系统而受批评，有人认为他的乐观主义忽视了权力结构的顽固性，但他对生命创造力的推崇仍为当代思想提供了激进资源。\n\n德勒兹最重要的代表作包括三部。首先，《差异与重复》（1968）是他独立完成的博士论文，系统阐述了差异本体论和重复的创造性，被视为后结构主义的核心文本。其次，《反俄狄浦斯：资本主义与精神分裂》（1972，与加塔利合著）是政治哲学的里程碑，批判精神分析并构建欲望政治学。最后，《千高原：资本主义与精神分裂续篇》（1980，与加塔利合著）以块茎式结构组织，探讨语言、艺术、战争机器等主题，是后现代思想的百科全书式作品。此外，《尼采与哲学》（1962）、《斯宾诺莎与实践哲学》（1970）和《电影1：运动-影像》（1983）也极具价值。德勒兹的哲学是思想的冒险，他鼓励我们“成为不可感知的”，在差异的海洋中游牧，这或许是他留给世界的最大遗产。",
  "wiki_url": "https://en.wikipedia.org/wiki/吉尔·德勒兹",
  "name": "吉尔·德勒兹"
}