{
  "era": "1619-1692年",
  "country": "中国",
  "school": "宋明理学",
  "bio": "王夫之，字而农，号姜斋，生于明万历四十七年（1619年），卒于清康熙三十一年（1692年），湖南衡阳人。他是明末清初最杰出的哲学家之一，与顾炎武、黄宗羲并称清初三大儒，晚年隐居湘西石船山，世称船山先生。其一生跨越明清鼎革的剧烈动荡，亲历王朝覆灭与异族入主，这种深重的历史创伤深刻塑造了他孤峭沉郁的思想品格。\\n王夫之出身于书香门第，自幼受家学熏陶，十四岁中秀才，二十四岁中举人。然而明末政治腐败、农民起义与满清铁骑的威胁彻底改变了他的命运。1644年李自成破北京、崇祯自缢，随后清军入关，王夫之在衡阳举兵抗清，兵败后辗转流亡。1650年，他投奔南明永历政权，因目睹朝廷党争与腐败，失望而归。此后他决意隐居，誓不仕清，在石船山麓筑草堂，以著述授徒终老。四十年间，他写下百余种、四百余卷著作，涵盖哲学、经学、史学、文学、政治等领域，其思想在清代长期湮没，至晚清才被重新发现，成为近代变革的重要思想资源。\\n王夫之的哲学体系以“气一元论”为核心，继承并发展了张载的气学。他反对程朱理学将“理”视为超越万物的绝对实体，也批判陆王心学“心外无物”的虚玄倾向，主张“气”是宇宙唯一实在，“理”不过是气运动变化的条理。他在《张子正蒙注》中强调：“气者，理之依也。气盛则理达。天积其健盛之气，故秩叙条理，精密变化而日新。”这意味着世界没有脱离物质的精神主宰，万物生成源于气的自我运动。他进而提出“太虚本动”的宇宙观，认为运动是气的根本属性，静止只是运动的暂态。这种动态自然观为其历史哲学和政治思想奠定了唯物主义基础。\\n在认识论上，王夫之强调“能必副其所”——主体认识（能）必须符合客观对象（所），批判佛教“消所入能”的唯心倾向。他主张“知行相资以为用”，既反对朱熹“知先行后”的割裂，也批评王阳明“知行合一”的混淆，认为知行是相互促进的过程，但“行”具有优先性：“行可兼知，而知不可兼行。”这种重实践的思想与其经世致用的学术品格紧密相连。\\n王夫之的历史哲学尤为深刻，他提出“理势合一”论，认为历史发展既有内在规律（理），又表现为不可抗拒的趋势（势）。他在《读通鉴论》中写道：“势相激而理随以易。”这意味着历史规律并非一成不变，而是随时代条件演变。他反对“三代圣王”的复古神话，主张“天下惟器”“道不离器”，指出制度、道德等“道”必须依附于具体历史情境的“器”。这种历史进化观使其成为传统儒家中最具辩证思维的哲学家之一。\\n政治思想上，王夫之具有鲜明的民本倾向。他批判绝对君权，提出“天下非一姓之私”“一姓之兴亡，私也；而生民之生死，公也”，认为王朝更替若不能造福民众，则其合法性值得质疑。他主张“严以治吏，宽以养民”，并设计“均田”以抑制兼并，这些思想对后世如谭嗣同、孙中山等改革者产生深远影响。\\n王夫之的学术气象博大，在经学上遍注群经，尤精于《周易》《尚书》《春秋》；在史学上以《读通鉴论》《宋论》开创了以史论政的范式；在文学上提出“诗以道性情”的审美观，反对形式主义。其文字艰深孤峭，充满遗民悲愤与理性思辨的交织，正如他在《自题墓石》中所言：“抱刘越石之孤忠，而命无从致；希张横渠之正学，而力不能企。”这种孤忠与正学并存的品格，使他在中国思想史上占据独特地位。\\n王夫之生前默默无闻，死后近两百年间著作仅在湖南少数士人中流传。至19世纪中叶，曾国藩、曾国荃兄弟刊刻《船山遗书》，其思想才广为人知。晚清维新派和革命派均从中汲取资源，章太炎称其“民族主义之师”，毛泽东早年亦深受其影响。王夫之将儒家道德理想与唯物主义哲学、进化史观相结合，为传统儒学注入了新的活力，堪称中国古典哲学的最后一位大家与近代思想的重要先驱。",
  "wiki_url": "https://en.wikipedia.org/wiki/王夫之",
  "name": "王夫之"
}