{
  "era": "1912年—2009年",
  "country": "挪威",
  "school": "深层生态学/分析哲学/斯宾诺莎主义",
  "bio": "阿恩·内斯（Arne Næss）是挪威著名哲学家、登山家，被誉为“深层生态学”（Deep Ecology）的创始人。他于1912年出生于奥斯陆，早年曾在巴黎、维也纳等地求学，深受逻辑实证主义与维特根斯坦哲学的影响。1939年，年仅27岁的内斯被任命为奥斯陆大学哲学教授，成为当时挪威最年轻的教授之一。他早期主要从事分析哲学与科学哲学研究，著有《解释与精确性》等作品，对语义学与沟通理论有独到贡献。然而，内斯最为人所知的贡献是他于1973年提出的“深层生态学”概念。这一思想源于他对环境危机的深刻反思，以及对浅层生态运动（仅关注污染与资源消耗的技术性解决）的不满。深层生态学主张，环境问题本质上是一个哲学与伦理问题，需要从根本上反思人类中心主义的世界观。内斯提出了“生态自我”（Ecological Self）的概念，认为人类并非与自然分离的孤立个体，而是生态系统的一部分，真正的自我实现应当包含对所有生命形式的认同与关怀。他借鉴了斯宾诺莎的泛神论思想、甘地的非暴力哲学以及佛教的慈悲理念，构建了一套以“生物圈平等主义”和“多样性共生”为核心的生态伦理体系。内斯还提出了“生态智慧”（Ecosophy T）这一个人化的哲学体系，强调每个人应当根据自身的生活经验与价值观，发展出与自然和谐共处的生存智慧。除了理论建构，内斯还积极参与环保运动，曾多次参与反对挪威水坝建设等抗议活动。他本人也是一位狂热的登山爱好者，曾多次攀登喜马拉雅山脉，这种与自然直接接触的经历深刻影响了他的哲学思考。内斯晚年依然活跃于公共领域，2009年去世，享年96岁。他的深层生态学思想对全球环保运动、生态哲学以及环境伦理学产生了深远影响，成为当代绿色政治与生态激进主义的重要理论源泉。",
  "wiki_url": "https://zh.wikipedia.org/wiki/阿恩·内斯",
  "name": "阿恩·内斯"
}