{
  "id": "17c85f942c78",
  "title": "法哲学原理",
  "author": "格奥尔格·威廉·弗里德里希·黑格尔",
  "region": "西方",
  "file_type": "epub",
  "file_size": 737675,
  "status": "available",
  "path": "西方/格奥尔格·威廉·弗里德里希·黑格尔/法哲学原理.epub",
  "tags": [
    "专著",
    "德国哲学"
  ],
  "updated_at": "2026-07-10T09:54:50.376964",
  "_download_url": "https://deepphilosophy.oss-cn-shanghai.aliyuncs.com/%E8%A5%BF%E6%96%B9/%E6%A0%BC%E5%A5%A5%E5%B0%94%E6%A0%BC%C2%B7%E5%A8%81%E5%BB%89%C2%B7%E5%BC%97%E9%87%8C%E5%BE%B7%E9%87%8C%E5%B8%8C%C2%B7%E9%BB%91%E6%A0%BC%E5%B0%94/%E6%B3%95%E5%93%B2%E5%AD%A6%E5%8E%9F%E7%90%86.epub",
  "summary": "《法哲学原理》是黑格尔客观精神哲学的系统阐述，出版于1821年，是他政治哲学与社会理论的代表作。本书并非单纯的法律著作，而是探讨自由意志在现实世界中如何实现自身的哲学体系。黑格尔从抽象法、道德、伦理三个层面展开论述，认为真正的自由不是任性妄为，而是在家庭、市民社会和国家这些伦理实体中获得的自觉认同。他提出“凡是合理的都是现实的，凡是现实的都是合理的”这一著名命题，强调理性与现实的辩证统一。本书的核心概念是“伦理生活”，即个人自由与社会规范的和解。黑格尔批判了自然权利论和契约论，主张国家是伦理理念的现实，是“神在地上的行走”。尽管书中对君主制和普鲁士国家的辩护常受争议，但其对市民社会与国家的区分、对劳动与需要的辩证分析，深刻影响了马克思的政治经济学批判。本书是理解现代政治哲学、法哲学和社会理论不可绕过的经典。",
  "keywords": [
    "专著",
    "德国哲学"
  ]
}