{"title": "index_split_021", "index": 21, "content": [{"type": "text", "value": "Table of Contents"}, {"type": "text", "value": "目录"}, {"type": "text", "value": "版权页"}, {"type": "text", "value": "相关内容"}, {"type": "text", "value": "出版说明"}, {"type": "text", "value": "插页"}, {"type": "text", "value": "致谢"}, {"type": "text", "value": "导言　批判的停顿：没有反对派的社会"}, {"type": "text", "value": "单向度的社会"}, {"type": "text", "value": "第一章　控制的新形式"}, {"type": "text", "value": "第二章　政治领域的封闭"}, {"type": "text", "value": "第三章　不幸意识的征服：压抑性的俗化趋势"}, {"type": "text", "value": "第四章　话语领域的封闭"}, {"type": "text", "value": "单向度的思想"}, {"type": "text", "value": "第五章　否定性的思维：被击败了的抗议逻辑"}, {"type": "text", "value": "第六章　从否定性思维到肯定性思维：技术合理性和统治的逻辑"}, {"type": "text", "value": "第七章　肯定性思维的胜利：单向度的哲学"}, {"type": "text", "value": "进行替代性选择的机会"}, {"type": "text", "value": "第八章　哲学的历史承诺"}, {"type": "text", "value": "第九章　解放的大变动"}, {"type": "text", "value": "第十章　结论"}, {"type": "text", "value": "译后记"}]}